Workbook

Sheet Guide
A1: Submission 2 - Test Case Design Sheet
A2: Playwright QA Automation for Insurance Order Entry Platform
A4: Purpose | B4: Converts the Submission 1 QA plan into detailed, traceable test cases for the Playwright automation build.
A5: Sheets | B5: Test Cases (the design sheet) | Coverage Summary | Risk Traceability | Validation ID Matrix | Test Data | Open Items | Review Log (v2 reviewer findings)
A6: Version | B6: v2 - reviewed against all Submission 2 documents; 32 cases and 3 columns added, 8 cases rewritten. See Review Log.
A7: Columns follow | B7: Guideline section 5: ID/title, module and requirement/risk/defect link, preconditions, steps, expected result, severity/priority, evidence required, automation status.
A8: Build Wave | B8: 1 = smoke path and critical checks to automate first | 2 = core validations | 3 = extended coverage. The 'Short-Cohort Set' column (Y) marks the 30-35 test fallback.
A9: Seeded defect links | B9: The seeded defect catalog was not supplied. Column G holds the defect class described in the problem statement; replace with catalog codes once available.
A10: Placeholders | B10: 'CONFIRM' marks values (limits, formats, counts) that must be verified in the running app. See Open Items.
A11: Automation Status | B11: All cases start as 'Not started'. Update as specs are written (Automated / In progress / Blocked).
A12: Extra columns | B12: Scenario Type (Positive/Negative/Boundary), Backend Cross-check (API/DB), Isolation / Cleanup (independence and shared-state notes).
A13: Editable cells | B13: Yellow cells on Open Items, and the Automation Status / Execution Result / Notes columns on Test Cases.
A15: Snapshot
A16: Total test cases | B16: =COUNTA('Test Cases'!A2:A174)
A17: Critical severity | B17: =COUNTIF('Test Cases'!L2:L174,"Critical")
A18: P1 priority | B18: =COUNTIF('Test Cases'!M2:M174,"P1")
A19: Wave 1 (smoke) | B19: =COUNTIF('Test Cases'!N2:N174,1)
A20: Validation IDs covered | B20: =COUNTIF('Validation ID Matrix'!E4:E72,"Covered")&" of "&COUNTA('Validation ID Matrix'!A4:A72)
A21: Open items | B21: =COUNTIF('Open Items'!F4:F40,"Open")

Sheet Test Cases
A1: Test Case ID | B1: Title | C1: Module | D1: Test Type | E1: Requirement / Validation ID | F1: Risk ID (Sub 1) | G1: Seeded Defect / Risk Link | H1: Preconditions | I1: Test Steps | J1: Test Data | K1: Expected Result | L1: Severity | M1: Priority | N1: Build Wave | O1: Tags | P1: Evidence Required | Q1: Automation Status | R1: Planned Spec File | S1: Execution Result | T1: Notes / Confirm | U1: Short-Cohort Set | V1: Scenario Type | W1: Backend Cross-check (API/DB) | X1: Isolation / Cleanup
A2: TC-AUTH-01 | B2: Valid agent logs in and lands on dashboard | C2: Authentication | D2: UI | E2: AUTH-V01 | F2: QR-01 | G2: Valid agent cannot log in after auth change | H2: App reachable; valid agent seeded; no active session. | I2: 1. Open /login. 2. Enter valid username and password. 3. Click Sign in. | J2: VALID_AGENT credentials from .env | K2: Redirected to /dashboard; URL ends with /dashboard; agent greeting/name visible; no error message. | L2: Critical | M2: P1 | N2: 1 | O2: @smoke @regression auth | P2: Screenshot of dashboard; trace on retry | Q2: Automated | R2: tests/auth/login.spec.ts | S2: Not run | U2: Y | V2: Positive | W2: API: POST /api/auth/login returns 200 + token/session | X2: Creates its own application via fixture (independent; unique generated data).
A3: TC-AUTH-02 | B3: Invalid password and unknown user show the same safe error and no session | C3: Authentication | D3: UI | E3: AUTH-V02 | F3: QR-01 | G3: Misleading login error message | H3: Valid agent exists; no session. | I3: 1. Open /login. 2. Enter valid username with wrong password; submit. 3. Enter an unknown username with any password; submit. 4. Try opening /dashboard. | J3: VALID_AGENT username + 'Wrong#Pass1'; 'no.such.user' + 'Wrong#Pass1' | K3: Stays on /login; invalid-credentials message visible (not 'account locked'); /dashboard still redirects to /login. | L3: High | M3: P1 | N3: 2 | O3: @regression auth | P3: Screenshot of error message | Q3: Automated | R3: tests/auth/login.spec.ts | S3: Not run | U3: N | V3: Negative | W3: - | X3: Creates its own application via fixture (independent; unique generated data).
A4: TC-AUTH-03 | B4: Blank username and password show mandatory-field errors | C4: Authentication | D4: UI | E4: AUTH-V03 | F4: QR-01 | G4: Mandatory login validation missing | H4: On /login with empty form. | I4: 1. Leave username and password empty. 2. Click Sign in. | J4: Empty values | K4: Field-level required errors on both fields; no request treated as successful; stays on /login. | L4: Medium | M4: P2 | N4: 2 | O4: @regression auth | P4: Screenshot of field errors | Q4: Automated | R4: tests/auth/login.spec.ts | S4: Not run | U4: N | V4: Negative | W4: - | X4: Creates its own application via fixture (independent; unique generated data).
A5: TC-AUTH-04 | B5: Logout clears session and protected routes redirect | C5: Authentication | D5: UI | E5: AUTH-V04 | F5: QR-01 | G5: No logout session clearing | H5: Logged in as valid agent. | I5: 1. Click Logout. 2. Confirm redirect to /login. 3. Use browser Back. 4. Open /dashboard directly. | J5: VALID_AGENT | K5: Redirected to /login after logout; Back and direct /dashboard access redirect to /login; session cookie/token cleared. | L5: Critical | M5: P1 | N5: 1 | O5: @smoke @regression auth | P5: Screenshot + cookie state note | Q5: Automated | R5: tests/auth/session.spec.ts | S5: Not run | U5: Y | V5: Positive | W5: API: GET /api/applications returns 401 after logout | X5: Creates its own application via fixture (independent; unique generated data).
A6: TC-AUTH-05 | B6: Direct access to protected routes without login is blocked | C6: Authentication | D6: UI | E6: AUTH-V05 | F6: QR-01 | G6: Dashboard reachable without login | H6: Fresh browser context, no cookies. | I6: 1. Open /dashboard in a fresh context. 2. Open /applications/new. 3. Open /applications/<id>/review. | J6: Seeded application id | K6: Each URL redirects to /login; no dashboard or application data is rendered. | L6: Critical | M6: P1 | N6: 1 | O6: @smoke @regression auth | P6: Screenshot; URL assertion in trace | Q6: Automated | R6: tests/auth/session.spec.ts | S6: Not run | U6: Y | V6: Negative | W6: - | X6: Creates its own application via fixture (independent; unique generated data).
A7: TC-AUTH-06 | B7: Locked user cannot access dashboard and sees accurate message | C7: Authentication | D7: UI | E7: AUTH-V06 | F7: QR-01 | G7: Misleading locked message | H7: Locked agent seeded. | I7: 1. Open /login. 2. Enter locked agent credentials. 3. Click Sign in. 4. Open /dashboard. | J7: LOCKED_AGENT credentials | K7: Account-locked message shown (accurate wording); no session created; /dashboard redirects to /login. | L7: High | M7: P1 | N7: 2 | O7: @regression auth | P7: Screenshot of locked message | Q7: Automated | R7: tests/auth/lockout.spec.ts | S7: Not run | U7: N | V7: Negative | W7: - | X7: Read-only: uses seeded locked agent.
A8: TC-AUTH-07 | B8: Account locks after five failed login attempts | C8: Authentication | D8: UI | E8: AUTH-V07 | F8: QR-01 | G8: Lockout not enforced at 5 attempts | H8: Dedicated non-locked test agent reserved for this test (lock state persists). | I8: 1. Submit wrong password 4 times; confirm normal invalid message each time. 2. Submit wrong password a 5th time. 3. Submit the CORRECT password. | J8: LOCKOUT_TEST_AGENT + wrong password | K8: After the 5th failure the account is locked; correct password is then rejected with locked message. Lock is NOT triggered on attempt 4. | L8: High | M8: P1 | N8: 2 | O8: @regression auth | P8: Screenshots after attempt 4, 5 and correct-password try | Q8: Automated | R8: tests/auth/lockout.spec.ts | S8: Not run | U8: Y | V8: Boundary | W8: DB (if approved): failed_attempts / locked flag | X8: Reserved LOCKOUT_TEST_AGENT; needs manual/admin unlock after run - run serially (workers=1 for this file).
A9: TC-AUTH-08 | B9: Weak password rejected during reset/change | C9: Authentication | D9: UI | E9: AUTH-V08 | F9: QR-01 | G9: Weak password accepted | H9: Reset/change password reachable (/forgot-password or profile). | I9: 1. Start reset for a test agent. 2. Enter new password from weak set (short, no digit, no special, common word). 3. Submit. | J9: 'abc', 'password', '12345678', 'Abcdefgh' | K9: Each weak value rejected with a clear policy message; password not changed (old password still works). | L9: High | M9: P1 | N9: 2 | O9: @regression auth | P9: Screenshot per weak value | Q9: Automated | R9: tests/auth/password.spec.ts | S9: Not run | U9: N | V9: Negative | W9: - | X9: Disposable agent; no password change persists on rejection.
A10: TC-AUTH-09 | B10: MFA agent completes login with simulated OTP | C10: Authentication | D10: UI | E10: Guideline: reset OTP / MFA | F10: QR-01 | G10: MFA/OTP bypass or wrong-code acceptance | H10: MFA agent seeded; OTP value known/simulated. | I10: 1. Login as MFA agent. 2. Enter wrong OTP, observe error. 3. Enter correct OTP. | J10: MFA_AGENT, OTP from .env (CONFIRM) | K10: Wrong OTP rejected; correct OTP reaches /dashboard. | L10: High | M10: P2 | N10: 3 | O10: @regression auth | P10: Screenshots of OTP error and dashboard | Q10: Automated | R10: tests/auth/mfa.spec.ts | S10: Not run | T10: Exact value/rule to be confirmed from app (see Open Items). | U10: N | V10: Positive | W10: - | X10: Creates its own application via fixture (independent; unique generated data).
A11: TC-AUTH-10 | B11: Password reset via OTP succeeds with valid new password | C11: Authentication | D11: UI | E11: Guideline: reset OTP | F11: QR-01 | G11: Reset OTP flow broken | H11: Disposable test agent; /forgot-password available. | I11: 1. Open /forgot-password; enter username/email. 2. Enter simulated OTP. 3. Set compliant new password. 4. Login with new password. | J11: Reset test agent; strong password | K11: Reset completes; login with new password succeeds; old password no longer works. | L11: Medium | M11: P3 | N11: 3 | O11: @regression auth | P11: Screenshots of each step | Q11: Automated | R11: tests/auth/password.spec.ts | S11: Not run | U11: N | V11: Positive | W11: - | X11: Disposable reset agent; password restored in afterEach.
A12: TC-AUTH-11 | B12: Reusing the same password on reset is rejected | C12: Authentication | D12: UI | E12: Guideline: same password reuse | F12: QR-01 | G12: Same-password reuse allowed | H12: Disposable test agent with known current password. | I12: 1. Start password reset/change. 2. Enter new password identical to current password. 3. Submit. | J12: Current password | K12: Request rejected with a 'cannot reuse' message; password unchanged. | L12: Medium | M12: P3 | N12: 3 | O12: @regression auth | P12: Screenshot of rejection | Q12: Automated | R12: tests/auth/password.spec.ts | S12: Not run | U12: N | V12: Negative | W12: - | X12: Disposable reset agent; password restored in afterEach.
A13: TC-AUTH-12 | B13: Expired/timed-out session forces re-login without data exposure | C13: Authentication | D13: UI | E13: Spec: session timeout / Sub 1 path 'Session expiration' | F13: QR-01, QR-10 | G13: Session not invalidated on timeout | H13: Logged in; session lifetime known (CONFIRM) or session cookie can be cleared/expired in the test. | I13: 1. Login and open an application step with unsaved edits. 2. Expire the session (wait for timeout or delete/expire the session cookie via context). 3. Click Save or navigate to another step. 4. Re-login. | J13: VALID_AGENT | K13: User is redirected to /login; no protected data rendered; API calls return 401; after re-login the previously SAVED data is intact and unsaved edits are not silently stored. | L13: High | M13: P2 | N13: 3 | O13: @regression auth | P13: Screenshot of redirect; network log showing 401 | Q13: Automated | R13: tests/auth/session.spec.ts | S13: Not run | T13: Exact value/rule to be confirmed from app (see Open Items). | U13: N | V13: Negative | W13: - | X13: Creates its own application via fixture (independent; unique generated data).
A14: TC-AUTH-13 | B14: Pending (unapproved) agent cannot access the platform | C14: Authentication | D14: UI | E14: Spec: user type 'pending agent' | F14: QR-01 | G14: Unapproved account gains access | H14: Pending agent seeded. | I14: 1. Login with pending agent credentials. 2. Open /dashboard. | J14: PENDING_AGENT | K14: Access is denied with an accurate pending-approval message (behavior CONFIRM); no session granted; /dashboard redirects to /login. | L14: High | M14: P2 | N14: 3 | O14: @regression auth | P14: Screenshot of message | Q14: Automated | R14: tests/auth/login.spec.ts | S14: Not run | T14: Exact value/rule to be confirmed from app (see Open Items). | U14: N | V14: Negative | W14: - | X14: Creates its own application via fixture (independent; unique generated data).
A15: TC-DASH-01 | B15: Dashboard shows summaries and New Application CTA after login | C15: Dashboard | D15: UI | E15: DASH-V01 | F15: QR-02 | G15: Dashboard summary missing/incorrect | H15: Logged in as valid agent with seeded applications. | I15: 1. Login as valid agent. 2. Observe dashboard. | J15: VALID_AGENT | K15: Draft summary, submitted summary and 'New application' CTA are visible. | L15: High | M15: P1 | N15: 1 | O15: @smoke @regression dashboard | P15: Screenshot of dashboard | Q15: Automated | R15: tests/dashboard/dashboard.spec.ts | S15: Not run | U15: Y | V15: Positive | W15: - | X15: Creates its own application via fixture (independent; unique generated data).
A16: TC-DASH-02 | B16: Agent sees only own applications (UI isolation) | C16: Dashboard | D16: UI | E16: DASH-V02 | F16: QR-02 | G16: Agent sees other agents' applications | H16: Two valid agents each with distinct seeded applications. | I16: 1. Login as agent A; record application IDs. 2. Logout; login as agent B; record IDs. 3. Compare lists. | J16: VALID_AGENT, SECOND_AGENT | K16: The two ID sets do not overlap; neither agent sees the other's applications. | L16: Critical | M16: P1 | N16: 2 | O16: @regression dashboard | P16: Screenshots of both lists | Q16: Automated | R16: tests/dashboard/dashboard.spec.ts | S16: Not run | U16: Y | V16: Negative | W16: - | X16: Read-only seeded applications of two agents.
A17: TC-DASH-03 | B17: New agent sees empty-state message and CTA | C17: Dashboard | D17: UI | E17: DASH-V03 | F17: QR-02 | G17: Empty state not handled | H17: New agent with zero applications. | I17: 1. Login as new agent. | J17: NEW_AGENT | K17: Empty-state copy shown; CTA to start a new application visible; no rows rendered. | L17: Low | M17: P3 | N17: 3 | O17: @regression dashboard | P17: Screenshot of empty state | Q17: Automated | R17: tests/dashboard/dashboard.spec.ts | S17: Not run | U17: N | V17: Positive | W17: - | X17: Read-only: new agent has no applications.
A18: TC-DASH-04 | B18: Draft can be resumed with previously entered data | C18: Dashboard | D18: UI | E18: DASH-V04 | F18: QR-02, QR-10 | G18: Draft not resumable / not persisted | H18: Seeded draft application owned by valid agent (or created in test). | I18: 1. From dashboard open the draft row. 2. Inspect the step and field values. | J18: Seeded draft id | K18: Application opens at the saved step; previously saved values are present and unchanged. | L18: High | M18: P1 | N18: 2 | O18: @regression dashboard | P18: Screenshot of restored values | Q18: Automated | R18: tests/dashboard/dashboard.spec.ts | S18: Not run | U18: N | V18: Positive | W18: API/DB: saved draft values | X18: Read-only seeded draft (or draft created by fixture).
A19: TC-DASH-05 | B19: Status filter returns correct rows (Draft/Submitted/Approved) | C19: Dashboard | D19: UI | E19: DASH-V05 | F19: QR-02 | G19: Filters return wrong rows | H19: Seeded draft, submitted and approved applications. | I19: 1. Apply Draft filter; read rows. 2. Apply Submitted filter. 3. Apply Approved filter. | J19: Seeded applications of each status | K19: Each filter shows only rows of that status; counts match seed data. | L19: Medium | M19: P2 | N19: 2 | O19: @regression dashboard | P19: Screenshot per filter | Q19: Automated | R19: tests/dashboard/dashboard.spec.ts | S19: Not run | U19: N | V19: Positive | W19: - | X19: Read-only seeded applications of each status.
A20: TC-DASH-06 | B20: Dashboard status matches status API for each application (status endpoint) | C20: Dashboard | D20: UI | E20: DASH-V06 | F20: QR-02, QR-09 | G20: Dashboard status differs from backend | H20: Valid agent logged in; session available to request context. | I20: 1. Read each dashboard row id + status. 2. Call GET /api/applications/{id}/status for each. 3. Compare. | J20: Seeded applications | K20: Every UI status equals API status. | L20: High | M20: P1 | N20: 2 | O20: @regression dashboard @api | P20: Table of UI vs API values in test log | Q20: Automated | R20: tests/dashboard/dashboard-api.spec.ts | S20: Not run | U20: N | V20: Positive | W20: API: GET /api/applications/{id}/status | X20: Creates its own application via fixture (independent; unique generated data).
A21: TC-DASH-07 | B21: Dashboard search finds an application by name/reference | C21: Dashboard | D21: UI | E21: Spec: dashboard search | F21: QR-02 | G21: Search returns wrong rows | H21: Seeded applications with distinct client names/references. | I21: 1. Search by a known client name. 2. Search by a known reference/ID. 3. Search for a non-existent term. 4. Clear search. | J21: Seeded names/references | K21: Matching rows only for 1 and 2; empty-result message for 3; full list restored after 4. | L21: Medium | M21: P2 | N21: 3 | O21: @regression dashboard | P21: Screenshots of each result state | Q21: Automated | R21: tests/dashboard/dashboard.spec.ts | S21: Not run | U21: N | V21: Positive | W21: - | X21: Creates its own application via fixture (independent; unique generated data).
A22: TC-DASH-08 | B22: Agent cannot open another agent's application by direct URL | C22: Dashboard | D22: UI | E22: Risk QR-02 (isolation) | F22: QR-02, QR-01 | G22: Agent sees other agents' applications | H22: Application id owned by agent A; agent B logged in. | I22: 1. As agent B open /applications/<A's id>. 2. Open /applications/<A's id>/review and /status. | J22: SECOND_AGENT + VALID_AGENT application id | K22: Access denied (403/404 page or redirect); no data of agent A is rendered on any of the three routes. | L22: Critical | M22: P1 | N22: 2 | O22: @regression dashboard auth | P22: Screenshots + network status codes | Q22: Automated | R22: tests/dashboard/isolation.spec.ts | S22: Not run | U22: Y | V22: Negative | W22: API: GET /api/applications/{otherId} returns 403/404 | X22: Creates its own application via fixture (independent; unique generated data).
A23: TC-DASH-09 | B23: Profile and Support pages load for a logged-in agent and are protected when logged out | C23: Dashboard | D23: UI | E23: Routes /profile, /support | F23: QR-01 | G23: Support/profile route unprotected or broken | H23: Valid agent; fresh context for the logged-out part. | I23: 1. Login; open /profile and /support. 2. In a fresh context open both URLs. | J23: VALID_AGENT | K23: Both pages render for the logged-in agent; logged-out access redirects to /login. | L23: Low | M23: P3 | N23: 3 | O23: @regression dashboard auth | P23: Screenshots | Q23: Automated | R23: tests/dashboard/dashboard.spec.ts | S23: Not run | U23: N | V23: Positive | W23: - | X23: Creates its own application via fixture (independent; unique generated data).
A24: TC-CLI-01 | B24: Valid insured personal information is saved and Next is enabled | C24: Client Information | D24: UI | E24: CLI-V01 | F24: QR-03, QR-10 | G24: Valid data blocks progression | H24: Logged in; new application started. | I24: 1. Fill all mandatory client fields with valid data. 2. Click Save/Next. 3. Return to the step. | J24: Generated client (age 40) | K24: Next step becomes enabled; saved values persist when step is revisited. | L24: High | M24: P1 | N24: 1 | O24: @smoke @regression client | P24: Screenshot of filled form + revisit | Q24: Automated | R24: tests/client-information/client.spec.ts | S24: Not run | U24: Y | V24: Positive | W24: API: GET client returns saved values | X24: Creates its own application via fixture (independent; unique generated data).
A25: TC-CLI-02 | B25: Mandatory personal fields show inline errors | C25: Client Information | D25: UI | E25: CLI-V02 | F25: QR-03 | G25: Mandatory fields skipped | H25: On Client step with empty form. | I25: 1. Leave name, DOB, gender, marital status, nationality, occupation, employer blank. 2. Click Next. | J25: Empty form | K25: Each required field shows an inline error; progression blocked. Also verify: the rejected value is not saved (reload or GET shows the previous/empty value). | L25: High | M25: P1 | N25: 2 | O25: @regression client | P25: Screenshot of errors | Q25: Automated | R25: tests/client-information/client.spec.ts | S25: Not run | U25: N | V25: Negative | W25: - | X25: Creates its own application via fixture (independent; unique generated data).
A26: TC-CLI-03 | B26: DOB making client under 18 is rejected | C26: Client Information | D26: UI | E26: CLI-V03 | F26: QR-03 | G26: Age eligibility rule missed | H26: On Client step. | I26: 1. Enter DOB = today minus 18 years plus 1 day (17y 364d). 2. Attempt to proceed. | J26: DOB 17y364d | K26: Eligibility error displayed; progression blocked. Also verify: the rejected value is not saved (reload or GET shows the previous/empty value). | L26: Critical | M26: P1 | N26: 2 | O26: @regression client | P26: Screenshot of error | Q26: Automated | R26: tests/client-information/dob.spec.ts | S26: Not run | U26: Y | V26: Boundary | W26: API: POST client rejects the same DOB (see TC-API-15) | X26: Creates its own application via fixture (independent; unique generated data).
A27: TC-CLI-04 | B27: DOB making client over 65 is rejected | C27: Client Information | D27: UI | E27: CLI-V04 | F27: QR-03 | G27: Age eligibility rule missed | H27: On Client step. | I27: 1. Enter DOB = 65 years and 1 day ago. 2. Attempt to proceed. | J27: DOB 65y+1d (CONFIRM inclusivity of 65) | K27: Eligibility error displayed; progression blocked. Also verify: the rejected value is not saved (reload or GET shows the previous/empty value). | L27: Critical | M27: P1 | N27: 2 | O27: @regression client | P27: Screenshot of error | Q27: Automated | R27: tests/client-information/dob.spec.ts | S27: Not run | T27: Exact value/rule to be confirmed from app (see Open Items). | U27: Y | V27: Boundary | W27: - | X27: Creates its own application via fixture (independent; unique generated data).
A28: TC-CLI-05 | B28: Future DOB is rejected | C28: Client Information | D28: UI | E28: CLI-V05 | F28: QR-03 | G28: Future DOB accepted | H28: On Client step. | I28: 1. Enter DOB = tomorrow. 2. Attempt to proceed. | J28: DOB tomorrow | K28: Validation error shown; progression blocked. Also verify: the rejected value is not saved (reload or GET shows the previous/empty value). | L28: Critical | M28: P1 | N28: 1 | O28: @smoke @regression client | P28: Screenshot of error | Q28: Automated | R28: tests/client-information/dob.spec.ts | S28: Not run | U28: Y | V28: Boundary | W28: API: POST client rejects future DOB | X28: Creates its own application via fixture (independent; unique generated data).
A29: TC-CLI-06 | B29: Boundary ages 18 and 65 are accepted (inclusive boundary) | C29: Client Information | D29: UI | E29: Guideline: DOB rules (BVA) | F29: QR-03 | G29: Boundary off-by-one | H29: On Client step. Inclusivity of 18 and 65 confirmed (see Open Items). | I29: 1. Enter DOB exactly 18 years ago; proceed. 2. Repeat with DOB exactly 65 years ago. | J29: DOB 18y0d and 65y0d | K29: Both DOBs accepted and progression allowed (adjust if spec says 65 exclusive). Also verify: the rejected value is not saved (reload or GET shows the previous/empty value). | L29: High | M29: P2 | N29: 3 | O29: @regression client | P29: Screenshots for both boundaries | Q29: Automated | R29: tests/client-information/dob.spec.ts | S29: Not run | U29: N | V29: Boundary | W29: - | X29: Creates its own application via fixture (independent; unique generated data).
A30: TC-CLI-07 | B30: Calculated age is displayed correctly from DOB | C30: Client Information | D30: UI | E30: Guideline: age visibility | F30: QR-03 | G30: Age miscalculated | H30: On Client step. | I30: 1. Enter a DOB giving a known age (including one whose birthday is later this year). 2. Read displayed age. | J30: DOB 40y and 39y364d | K30: Displayed age equals expected age computed by test helper for each DOB. | L30: High | M30: P2 | N30: 2 | O30: @regression client | P30: Screenshot of age field | Q30: Automated | R30: tests/client-information/dob.spec.ts | S30: Not run | U30: N | V30: Positive | W30: - | X30: Creates its own application via fixture (independent; unique generated data).
A31: TC-CLI-08 | B31: Invalid name formats are rejected | C31: Client Information | D31: UI | E31: Guideline: name validation | F31: QR-03 | G31: Invalid names accepted | H31: On Client step. | I31: 1. Enter names with digits/symbols (e.g. 'J0hn#', '123', single space). 2. Attempt to proceed. | J31: 'J0hn#', '12345', ' ' | K31: Name validation error shown for each invalid value; valid name 'Anita Rao' accepted. Also verify: the rejected value is not saved (reload or GET shows the previous/empty value). | L31: Medium | M31: P2 | N31: 3 | O31: @regression client | P31: Screenshot per invalid value | Q31: Automated | R31: tests/client-information/client.spec.ts | S31: Not run | U31: N | V31: Negative | W31: - | X31: Creates its own application via fixture (independent; unique generated data).
A32: TC-CLI-09 | B32: Impossible or malformed DOB values are rejected | C32: Client Information | D32: UI | E32: Guideline: date of birth rules | F32: QR-03 | G32: Invalid DOB accepted | H32: On Client step. | I32: 1. Enter 31-Feb, 00/00/0000, text 'abc', and a year before 1900. 2. Attempt to proceed. | J32: '31-02-1990', '00-00-0000', 'abc', '01-01-1850' | K32: Each value is rejected with a date-format/range error; no age is calculated or displayed. Also verify: the rejected value is not saved (reload or GET shows the previous/empty value). | L32: Medium | M32: P2 | N32: 3 | O32: @regression client | P32: Screenshot per value | Q32: Automated | R32: tests/client-information/dob.spec.ts | S32: Not run | U32: N | V32: Boundary | W32: - | X32: Creates its own application via fixture (independent; unique generated data).
A33: TC-ADDR-01 | B33: Same-as-residential copies address to mailing | C33: Address & Contact | D33: UI | E33: CLI-V06 | F33: QR-03 | G33: Same-as-residential not copied | H33: On Address & Contact step. | I33: 1. Fill residential address. 2. Tick 'same as residential'. 3. Compare mailing fields. 4. Save and reopen. | J33: Generated address | K33: All mailing fields equal residential values; values persist after reopening. | L33: Medium | M33: P1 | N33: 1 | O33: @smoke @regression address | P33: Screenshot of copied fields | Q33: Automated | R33: tests/client-information/address.spec.ts | S33: Not run | U33: Y | V33: Positive | W33: - | X33: Creates its own application via fixture (independent; unique generated data).
A34: TC-ADDR-02 | B34: Unticking same-as-residential makes mailing editable and independent | C34: Address & Contact | D34: UI | E34: Guideline: same-as-residential | F34: QR-03 | G34: Mailing locked/overwritten | H34: Same-as-residential ticked. | I34: 1. Untick the checkbox. 2. Edit a mailing field. 3. Edit a residential field. | J34: Generated address | K34: Mailing fields become editable; editing residential no longer overwrites edited mailing values. | L34: Low | M34: P3 | N34: 3 | O34: @regression address | P34: Screenshot | Q34: Automated | R34: tests/client-information/address.spec.ts | S34: Not run | U34: N | V34: Positive | W34: - | X34: Creates its own application via fixture (independent; unique generated data).
A35: TC-ADDR-03 | B35: Invalid ZIP/postal code is rejected | C35: Address & Contact | D35: UI | E35: Guideline: ZIP validation | F35: QR-03 | G35: ZIP validation gaps | H35: On Address step. | I35: 1. Enter invalid ZIP values. 2. Attempt to proceed. | J35: 'ABCDE', '123', '1234567', blank | K35: Error shown per invalid ZIP; valid ZIP for the chosen state accepted. Also verify: the rejected value is not saved (reload or GET shows the previous/empty value). | L35: Medium | M35: P2 | N35: 2 | O35: @regression address | P35: Screenshot per value | Q35: Automated | R35: tests/client-information/address.spec.ts | S35: Not run | U35: N | V35: Negative | W35: - | X35: Creates its own application via fixture (independent; unique generated data).
A36: TC-ADDR-04 | B36: State is mandatory and ZIP/state mismatch is flagged | C36: Address & Contact | D36: UI | E36: Guideline: state validation | F36: QR-03 | G36: State validation gaps | H36: On Address step. | I36: 1. Leave state unselected; proceed. 2. Select a state and a ZIP belonging to another state (if app validates). | J36: State/ZIP pairs (CONFIRM rule) | K36: Missing state blocks progression; mismatch behavior matches confirmed rule. Also verify: the rejected value is not saved (reload or GET shows the previous/empty value). | L36: Medium | M36: P3 | N36: 3 | O36: @regression address | P36: Screenshot | Q36: Automated | R36: tests/client-information/address.spec.ts | S36: Not run | T36: Exact value/rule to be confirmed from app (see Open Items). | U36: N | V36: Negative | W36: - | X36: Creates its own application via fixture (independent; unique generated data).
A37: TC-ADDR-05 | B37: Invalid email format is rejected | C37: Address & Contact | D37: UI | E37: CLI-V07 | F37: QR-03 | G37: Email validation gap | H37: On Contact section. | I37: 1. Enter invalid emails. 2. Attempt to proceed. | J37: 'abc', 'a@b', 'a@@b.com', 'a b@c.com' | K37: Inline email error per value; valid email accepted. Also verify: the rejected value is not saved (reload or GET shows the previous/empty value). | L37: Medium | M37: P2 | N37: 2 | O37: @regression address | P37: Screenshot per value | Q37: Automated | R37: tests/client-information/contact.spec.ts | S37: Not run | U37: N | V37: Negative | W37: - | X37: Creates its own application via fixture (independent; unique generated data).
A38: TC-ADDR-06 | B38: Invalid phone number is rejected | C38: Address & Contact | D38: UI | E38: CLI-V07 | F38: QR-03 | G38: Phone validation gap | H38: On Contact section. | I38: 1. Enter invalid mobile/alternate numbers. 2. Attempt to proceed. | J38: '12345', 'abcdefghij', '+', 11-digit value (CONFIRM format) | K38: Inline phone error per value; valid number accepted. Also verify: the rejected value is not saved (reload or GET shows the previous/empty value). | L38: Medium | M38: P2 | N38: 2 | O38: @regression address | P38: Screenshot per value | Q38: Automated | R38: tests/client-information/contact.spec.ts | S38: Not run | T38: Exact value/rule to be confirmed from app (see Open Items). | U38: N | V38: Negative | W38: - | X38: Creates its own application via fixture (independent; unique generated data).
A39: TC-ADDR-07 | B39: At least one contact method / preferred mode is required | C39: Address & Contact | D39: UI | E39: Guideline: mandatory contact method | F39: QR-03 | G39: No contact method required | H39: On Contact section. | I39: 1. Clear email, mobile and alternate phone. 2. Leave preferred communication mode empty. 3. Proceed. | J39: Empty contact data | K39: Validation requires a contact method / preferred mode; progression blocked. Also verify: the rejected value is not saved (reload or GET shows the previous/empty value). | L39: Medium | M39: P2 | N39: 3 | O39: @regression address | P39: Screenshot | Q39: Automated | R39: tests/client-information/contact.spec.ts | S39: Not run | U39: N | V39: Negative | W39: - | X39: Creates its own application via fixture (independent; unique generated data).
A40: TC-KYC-01 | B40: SSN is masked after entry (only last four visible) | C40: KYC & Financial | D40: UI | E40: CLI-V08 | F40: QR-04 | G40: SSN not masked | H40: On KYC step. | I40: 1. Enter a synthetic SSN. 2. Tab away / save. 3. Reopen the step. | J40: Synthetic SSN 123-45-6789 (fake) | K40: Only last four digits visible after entry and on reopen; full value not displayed. | L40: Critical | M40: P1 | N40: 2 | O40: @regression kyc | P40: Screenshot (use fake SSN only) | Q40: Automated | R40: tests/client-information/kyc.spec.ts | S40: Not run | U40: Y | V40: Positive | W40: API/DB: stored SSN masked/encrypted (read-only) | X40: Creates its own application via fixture (independent; unique generated data).
A41: TC-KYC-02 | B41: ID number validated by ID type | C41: KYC & Financial | D41: UI | E41: Risk QR-04 | F41: QR-04 | G41: ID format not validated by type | H41: On KYC step; ID types available (CONFIRM list). | I41: 1. For each ID type enter a number in the wrong format. 2. Attempt to proceed. 3. Enter correct format. | J41: Wrong/right format per ID type | K41: Wrong formats rejected with type-specific error; correct formats accepted. Also verify: the rejected value is not saved (reload or GET shows the previous/empty value). | L41: High | M41: P2 | N41: 3 | O41: @regression kyc | P41: Screenshot per ID type | Q41: Automated | R41: tests/client-information/kyc.spec.ts | S41: Not run | T41: Exact value/rule to be confirmed from app (see Open Items). | U41: N | V41: Negative | W41: - | X41: Creates its own application via fixture (independent; unique generated data).
A42: TC-KYC-03 | B42: KYC upload rejects unsupported file type | C42: KYC & Financial | D42: UI | E42: CLI-V09 | F42: QR-04, QR-08 | G42: Bad file types accepted | H42: On KYC document upload control. | I42: 1. Upload sample.exe. 2. Upload sample.txt. | J42: invalid-type files from fixtures/files | K42: Both uploads rejected with unsupported-type message; no document listed as uploaded. Also verify: the rejected value is not saved (reload or GET shows the previous/empty value). | L42: High | M42: P1 | N42: 2 | O42: @regression kyc | P42: Screenshot of error | Q42: Automated | R42: tests/client-information/kyc.spec.ts | S42: Not run | U42: N | V42: Negative | W42: - | X42: Creates its own application via fixture (independent; unique generated data).
A43: TC-KYC-04 | B43: PEP 'Yes' makes details mandatory | C43: KYC & Financial | D43: UI | E43: CLI-V10 | F43: QR-04 | G43: PEP details optional | H43: On Compliance section. | I43: 1. Select PEP = Yes. 2. Leave details blank and proceed. 3. Fill details and proceed. | J43: PEP detail text | K43: Details field appears and is mandatory; blank blocks progression; filled allows. Also verify: the rejected value is not saved (reload or GET shows the previous/empty value). | L43: High | M43: P1 | N43: 2 | O43: @regression kyc | P43: Screenshots before/after | Q43: Automated | R43: tests/client-information/kyc.spec.ts | S43: Not run | U43: N | V43: Negative | W43: - | X43: Creates its own application via fixture (independent; unique generated data).
A44: TC-KYC-05 | B44: Income vs premium affordability validation is applied | C44: KYC & Financial | D44: UI | E44: Risk QR-04 / QR-05 | F44: QR-04, QR-05 | G44: Affordability not applied | H44: Client with low annual income; product configured with high premium. | I44: 1. Enter low income on KYC step. 2. Configure product so annual premium exceeds affordability threshold (CONFIRM). 3. Proceed to review. | J44: Income 100000 (example), high face value | K44: Affordability warning or block displayed according to confirmed rule. Also verify: the rejected value is not saved (reload or GET shows the previous/empty value). | L44: High | M44: P2 | N44: 3 | O44: @regression kyc | P44: Screenshot of warning | Q44: Automated | R44: tests/client-information/kyc.spec.ts | S44: Not run | T44: Exact value/rule to be confirmed from app (see Open Items). | U44: N | V44: Negative | W44: - | X44: Creates its own application via fixture (independent; unique generated data).
A45: TC-KYC-06 | B45: Incomplete compliance declaration blocks progression | C45: KYC & Financial | D45: UI | E45: Functional spec: Compliance | F45: QR-04 | G45: Declaration not enforced | H45: On KYC step. | I45: 1. Leave PEP/declaration unanswered. 2. Proceed. | J45: Empty declaration | K45: Progression blocked with message on unanswered declaration. Also verify: the rejected value is not saved (reload or GET shows the previous/empty value). | L45: Medium | M45: P2 | N45: 3 | O45: @regression kyc | P45: Screenshot | Q45: Automated | R45: tests/client-information/kyc.spec.ts | S45: Not run | U45: N | V45: Negative | W45: - | X45: Creates its own application via fixture (independent; unique generated data).
A46: TC-KYC-07 | B46: Sensitive ID is not returned unmasked in client API response | C46: KYC & Financial | D46: API | E46: Spec: SSN masking | F46: QR-04 | G46: SSN exposed in response | H46: Application with saved SSN; authenticated request context. | I46: 1. GET /api/applications/{id}/client. 2. Inspect SSN field(s). | J46: Application from TC-KYC-01 | K46: SSN returned masked (last four only) or absent; full value not present anywhere in body. | L46: Critical | M46: P1 | N46: 2 | O46: @api @regression kyc | P46: Response body saved with value redacted | Q46: Automated | R46: tests/api/client-api.spec.ts | S46: Not run | U46: Y | V46: Positive | W46: - | X46: Creates its own application via fixture (independent; unique generated data).
A47: TC-KYC-08 | B47: Financial suitability fields are mandatory and numeric-validated | C47: KYC & Financial | D47: UI | E47: Spec: income, net worth, source of funds, risk profile | F47: QR-04 | G47: Financial fields skipped / invalid values accepted | H47: On KYC step. | I47: 1. Leave income, net worth, source of funds and risk profile empty; proceed. 2. Enter negative and non-numeric income/net worth; proceed. 3. Enter valid values. | J47: Empty; -1; 'abc'; valid income and net worth | K47: Empty and invalid values blocked with field-level errors; valid values accepted. Also verify: the rejected value is not saved (reload or GET shows the previous/empty value). | L47: High | M47: P2 | N47: 2 | O47: @regression kyc | P47: Screenshots | Q47: Automated | R47: tests/client-information/kyc.spec.ts | S47: Not run | U47: N | V47: Negative | W47: - | X47: Creates its own application via fixture (independent; unique generated data).
A48: TC-KYC-09 | B48: ID issue/expiry dates are validated | C48: KYC & Financial | D48: UI | E48: Spec: ID issue/expiry date | F48: QR-04 | G48: Expired or inconsistent ID accepted | H48: On KYC step. | I48: 1. Enter an expiry date in the past. 2. Enter expiry earlier than issue date. 3. Enter issue date in the future. 4. Enter valid dates. | J48: Past expiry; expiry < issue; future issue; valid | K48: Cases 1-3 rejected with clear errors (rule CONFIRM); valid dates accepted. Also verify: the rejected value is not saved (reload or GET shows the previous/empty value). | L48: Medium | M48: P2 | N48: 3 | O48: @regression kyc | P48: Screenshots | Q48: Automated | R48: tests/client-information/kyc.spec.ts | S48: Not run | T48: Exact value/rule to be confirmed from app (see Open Items). | U48: N | V48: Negative | W48: - | X48: Creates its own application via fixture (independent; unique generated data).
A49: TC-PROD-01 | B49: Catalog lists expected Whole Life products | C49: Product & Policy | D49: UI | E49: PROD-V01 | F49: QR-05 | G49: Product missing/wrong in catalog | H49: Logged in; /products reachable. | I49: 1. Open /products. 2. Read product cards. | J49: Expected product names (from seed, CONFIRM) | K49: Expected active products are shown with names and key details. | L49: Medium | M49: P2 | N49: 2 | O49: @regression product | P49: Screenshot of catalog | Q49: Automated | R49: tests/product-selection/catalog.spec.ts | S49: Not run | T49: Exact value/rule to be confirmed from app (see Open Items). | U49: N | V49: Positive | W49: - | X49: Creates its own application via fixture (independent; unique generated data).
A50: TC-PROD-02 | B50: Product detail page shows features, eligibility and limits | C50: Product & Policy | D50: UI | E50: PROD-V02 | F50: QR-05 | G50: Product detail incorrect | H50: On /products. | I50: 1. Click a product. 2. Read detail page. | J50: First active product | K50: /products/:id opens; features, eligibility and coverage limits visible. | L50: Medium | M50: P3 | N50: 2 | O50: @regression product | P50: Screenshot of detail page | Q50: Automated | R50: tests/product-selection/catalog.spec.ts | S50: Not run | U50: N | V50: Positive | W50: - | X50: Creates its own application via fixture (independent; unique generated data).
A51: TC-PROD-03 | B51: Face value below minimum is rejected | C51: Product & Policy | D51: UI | E51: PROD-V03 | F51: QR-05 | G51: Face value minimum not enforced | H51: Product selected; limits known (CONFIRM). | I51: 1. Enter face value = min - 1. 2. Attempt to save. 3. Enter exactly min. | J51: MIN_FACE_VALUE (from product detail) | K51: min-1 rejected with validation; exactly min accepted. Also verify: the rejected value is not saved (reload or GET shows the previous/empty value). | L51: High | M51: P1 | N51: 2 | O51: @regression product | P51: Screenshots of both boundaries | Q51: Automated | R51: tests/product-selection/face-value.spec.ts | S51: Not run | T51: Exact value/rule to be confirmed from app (see Open Items). | U51: N | V51: Boundary | W51: - | X51: Creates its own application via fixture (independent; unique generated data).
A52: TC-PROD-04 | B52: Face value above maximum is rejected | C52: Product & Policy | D52: UI | E52: PROD-V04 | F52: QR-05 | G52: Face value maximum not enforced | H52: Product selected; limits known. | I52: 1. Enter face value = max + 1. 2. Attempt to save. 3. Enter exactly max. | J52: MAX_FACE_VALUE | K52: max+1 rejected with validation; exactly max accepted. Also verify: the rejected value is not saved (reload or GET shows the previous/empty value). | L52: High | M52: P1 | N52: 2 | O52: @regression product | P52: Screenshots of both boundaries | Q52: Automated | R52: tests/product-selection/face-value.spec.ts | S52: Not run | U52: N | V52: Boundary | W52: - | X52: Creates its own application via fixture (independent; unique generated data).
A53: TC-PROD-05 | B53: Premium recalculates when frequency changes | C53: Product & Policy | D53: UI | E53: PROD-V05 | F53: QR-05 | G53: Premium not recalculated on frequency change | H53: Valid face value entered. | I53: 1. Note premium for Monthly. 2. Switch to Quarterly, Semi-annual, Annual and note each. | J53: Fixed face value | K53: Displayed premium changes for each frequency and matches API/formula once confirmed. | L53: High | M53: P1 | N53: 2 | O53: @regression product | P53: Table of frequency vs premium in log | Q53: Automated | R53: tests/product-selection/premium.spec.ts | S53: Not run | U53: Y | V53: Positive | W53: API: premium field (if exposed) | X53: Creates its own application via fixture (independent; unique generated data).
A54: TC-PROD-06 | B54: Review-page premium equals configuration-page premium | C54: Product & Policy | D54: UI | E54: PROD-V06 | F54: QR-05 | G54: Review premium differs from config | H54: Application configured through product step. | I54: 1. Capture premium on configuration page. 2. Navigate to /review. 3. Compare. | J54: Configured application | K54: Premium values are identical (same currency/rounding). | L54: High | M54: P1 | N54: 2 | O54: @regression product | P54: Screenshots of both pages | Q54: Automated | R54: tests/product-selection/premium.spec.ts | S54: Not run | U54: Y | V54: Positive | W54: API: premium on review payload | X54: Creates its own application via fixture (independent; unique generated data).
A55: TC-PROD-07 | B55: Suitability warning appears for risk-profile mismatch | C55: Product & Policy | D55: UI | E55: PROD-V07 | F55: QR-05 | G55: No suitability warning | H55: KYC risk profile set to conservative; high-risk product/amount chosen. | I55: 1. Set risk profile on KYC. 2. Select mismatching product/face value. | J55: Risk profile = low (CONFIRM) | K55: Suitability warning visible. Also verify: the rejected value is not saved (reload or GET shows the previous/empty value). | L55: Medium | M55: P2 | N55: 3 | O55: @regression product | P55: Screenshot of warning | Q55: Automated | R55: tests/product-selection/suitability.spec.ts | S55: Not run | T55: Exact value/rule to be confirmed from app (see Open Items). | U55: N | V55: Negative | W55: - | X55: Creates its own application via fixture (independent; unique generated data).
A56: TC-PROD-08 | B56: Inactive product cannot be selected | C56: Product & Policy | D56: UI | E56: Guideline: inactive products | F56: QR-05 | G56: Inactive product selectable | H56: At least one inactive product in seed data (CONFIRM). | I56: 1. Look for inactive product in catalog. 2. Try to select/configure it (UI and direct URL). | J56: Inactive product id | K56: Inactive product is hidden or select action disabled; direct URL/API does not allow configuration. Also verify: the rejected value is not saved (reload or GET shows the previous/empty value). | L56: High | M56: P2 | N56: 3 | O56: @regression product | P56: Screenshot | Q56: Automated | R56: tests/product-selection/catalog.spec.ts | S56: Not run | T56: Exact value/rule to be confirmed from app (see Open Items). | U56: N | V56: Negative | W56: - | X56: Creates its own application via fixture (independent; unique generated data).
A57: TC-PROD-09 | B57: Saved product configuration persists after reopening | C57: Product & Policy | D57: UI | E57: Guideline: persistence checks | F57: QR-10 | G57: Configuration not persisted | H57: Application with product configured and saved. | I57: 1. Save product configuration. 2. Go to dashboard and resume. 3. Open product step. | J57: Face value, frequency, payment term, policy term | K57: All configured values and premium are restored exactly. | L57: High | M57: P2 | N57: 3 | O57: @regression product | P57: Screenshot of restored values | Q57: Automated | R57: tests/product-selection/persistence.spec.ts | S57: Not run | U57: N | V57: Positive | W57: - | X57: Creates its own application via fixture (independent; unique generated data).
A58: TC-PROD-10 | B58: Product eligibility is validated against client age | C58: Product & Policy | D58: UI | E58: Problem statement 2.2: product eligibility vs age | F58: QR-05 | G58: Product eligibility not validated against client age | H58: Product with an age eligibility range visible on detail page (CONFIRM). | I58: 1. Create application with client age outside the product's range. 2. Try to select that product. 3. Repeat with an in-range age. | J58: Out-of-range and in-range ages | K58: Out-of-range selection blocked or warned; in-range accepted. Also verify: the rejected value is not saved (reload or GET shows the previous/empty value). | L58: High | M58: P1 | N58: 2 | O58: @regression product | P58: Screenshots | Q58: Automated | R58: tests/product-selection/eligibility.spec.ts | S58: Not run | T58: Exact value/rule to be confirmed from app (see Open Items). | U58: N | V58: Negative | W58: - | X58: Creates its own application via fixture (independent; unique generated data).
A59: TC-PROD-11 | B59: Payment term and policy term options follow product rules | C59: Product & Policy | D59: UI | E59: Spec: payment term / policy term | F59: QR-05 | G59: Term rules not enforced | H59: Product selected. | I59: 1. Open payment term dropdown; read options. 2. Select each option and check the dependent policy-term display (Whole Life / to Age 100). 3. Attempt an unsupported combination if the UI allows. | J59: All payment term options | K59: Dropdown values match product detail/API; policy term display follows the rule; unsupported combos blocked. | L59: Medium | M59: P2 | N59: 3 | O59: @regression product | P59: Screenshot of options | Q59: Automated | R59: tests/product-selection/terms.spec.ts | S59: Not run | U59: N | V59: Positive | W59: - | X59: Creates its own application via fixture (independent; unique generated data).
A60: TC-PROD-12 | B60: Invalid face value inputs (zero, negative, non-numeric, decimals) are rejected | C60: Product & Policy | D60: UI | E60: Spec: face value boundary validation | F60: QR-05 | G60: Face value validation gaps | H60: Product selected. | I60: 1. Enter 0, -1000, 'abc', 100000.55 (if integers only), and blank. 2. Attempt to save. | J60: 0; -1000; 'abc'; 100000.55; blank | K60: Each value rejected with a face-value error; premium not calculated from invalid input. Also verify: the rejected value is not saved (reload or GET shows the previous/empty value). | L60: Medium | M60: P2 | N60: 3 | O60: @regression product | P60: Screenshot per value | Q60: Automated | R60: tests/product-selection/face-value.spec.ts | S60: Not run | U60: N | V60: Boundary | W60: - | X60: Creates its own application via fixture (independent; unique generated data).
A61: TC-PROD-13 | B61: Product search/filter in catalog returns correct products | C61: Product & Policy | D61: UI | E61: ProductCatalogPage: product search | F61: QR-05 | G61: Search returns wrong products | H61: On /products. | I61: 1. Search for an existing product name. 2. Search for a non-existent term. 3. Clear the search. | J61: Existing / non-existent term | K61: Only matching products for 1; empty-result message for 2; full catalog after 3. | L61: Low | M61: P3 | N61: 3 | O61: @regression product | P61: Screenshots | Q61: Automated | R61: tests/product-selection/catalog.spec.ts | S61: Not run | U61: N | V61: Positive | W61: - | X61: Creates its own application via fixture (independent; unique generated data).
A62: TC-PROD-14 | B62: Premium shown in UI equals premium from API (reconciliation) | C62: Product & Policy | D62: UI | E62: Spec: premium UI/API reconciliation | F62: QR-05, QR-09 | G62: UI and API premium differ | H62: Configured application; premium exposed by API (CONFIRM field). | I62: 1. Configure face value + frequency. 2. Read UI premium. 3. GET application/product data from API and read premium. 4. Compare for all four frequencies. | J62: Fixed configuration x 4 frequencies | K62: UI premium equals API premium for each frequency (same rounding). | L62: High | M62: P2 | N62: 3 | O62: @regression product @api | P62: UI vs API comparison table | Q62: Automated | R62: tests/product-selection/premium.spec.ts | S62: Not run | T62: Exact value/rule to be confirmed from app (see Open Items). | U62: N | V62: Positive | W62: - | X62: Creates its own application via fixture (independent; unique generated data).
A63: TC-RID-01 | B63: Eligible protection rider (ADB) can be added | C63: Riders | D63: UI | E63: RIDER-V01 | F63: QR-06 | G63: Rider add fails | H63: Application at Riders step; client age eligible. | I63: 1. Select the ADB rider. 2. Check premium summary. | J63: Eligible client age 40 | K63: Rider appears in premium summary. | L63: High | M63: P1 | N63: 1 | O63: @smoke @regression rider | P63: Screenshot of premium summary | Q63: Automated | R63: tests/riders/riders.spec.ts | S63: Not run | U63: Y | V63: Positive | W63: - | X63: Creates its own application via fixture (independent; unique generated data).
A64: TC-RID-02 | B64: Rider coverage cannot exceed base face value | C64: Riders | D64: UI | E64: RIDER-V02 | F64: QR-06 | G64: Rider coverage above face value | H64: Face value set (e.g. 100000). | I64: 1. Select rider with editable coverage. 2. Enter coverage = face value + 1. 3. Enter coverage = face value. | J64: Coverage FV+1 and FV | K64: FV+1 rejected with validation; FV accepted. Also verify: the rejected value is not saved (reload or GET shows the previous/empty value). | L64: High | M64: P1 | N64: 2 | O64: @regression rider | P64: Screenshots | Q64: Automated | R64: tests/riders/riders.spec.ts | S64: Not run | U64: Y | V64: Boundary | W64: - | X64: Creates its own application via fixture (independent; unique generated data).
A65: TC-RID-03 | B65: Age-ineligible rider cannot be added | C65: Riders | D65: UI | E65: RIDER-V03 | F65: QR-06 | G65: Age-ineligible rider added | H65: Client age outside rider's allowed range (CONFIRM limits). | I65: 1. Reach Riders step with out-of-range age client. 2. Try to select rider. | J65: Client near upper age limit | K65: Rider disabled or error shown; not added to summary. Also verify: the rejected value is not saved (reload or GET shows the previous/empty value). | L65: High | M65: P2 | N65: 3 | O65: @regression rider | P65: Screenshot | Q65: Automated | R65: tests/riders/riders.spec.ts | S65: Not run | T65: Exact value/rule to be confirmed from app (see Open Items). | U65: N | V65: Negative | W65: - | X65: Creates its own application via fixture (independent; unique generated data).
A66: TC-RID-04 | B66: Maximum rider count is enforced | C66: Riders | D66: UI | E66: RIDER-V04 | F66: QR-06 | G66: Max rider count ignored | H66: Max count known (CONFIRM). | I66: 1. Add riders until max. 2. Try to add one more. | J66: Riders list | K66: Blocking message shown; extra rider not added. Also verify: the rejected value is not saved (reload or GET shows the previous/empty value). | L66: High | M66: P2 | N66: 3 | O66: @regression rider | P66: Screenshot of block message | Q66: Automated | R66: tests/riders/riders.spec.ts | S66: Not run | T66: Exact value/rule to be confirmed from app (see Open Items). | U66: N | V66: Negative | W66: - | X66: Creates its own application via fixture (independent; unique generated data).
A67: TC-RID-05 | B67: Mutually exclusive waiver riders cannot both be selected | C67: Riders | D67: UI | E67: RIDER-V05 | F67: QR-06 | G67: Exclusive waivers both allowed | H67: Two waiver riders exist. | I67: 1. Select waiver rider A. 2. Try to select waiver rider B. | J67: Waiver riders | K67: Waiver B disabled or blocked while A selected. Also verify: the rejected value is not saved (reload or GET shows the previous/empty value). | L67: High | M67: P1 | N67: 2 | O67: @regression rider | P67: Screenshot | Q67: Automated | R67: tests/riders/riders.spec.ts | S67: Not run | U67: Y | V67: Negative | W67: - | X67: Creates its own application via fixture (independent; unique generated data).
A68: TC-RID-06 | B68: Critical illness rider triggers health questionnaire | C68: Riders | D68: UI | E68: RIDER-V06 | F68: QR-06 | G68: CI questionnaire missing | H68: CI rider available to client. | I68: 1. Select Critical Illness rider. | J68: CI rider | K68: Health questionnaire section appears and is required. | L68: Medium | M68: P2 | N68: 2 | O68: @regression rider | P68: Screenshot of questionnaire | Q68: Automated | R68: tests/riders/riders.spec.ts | S68: Not run | U68: N | V68: Positive | W68: - | X68: Creates its own application via fixture (independent; unique generated data).
A69: TC-RID-07 | B69: Rider premium is itemized and total updates | C69: Riders | D69: UI | E69: RIDER-V07 | F69: QR-06, QR-05 | G69: Premium not itemized | H69: Base premium known. | I69: 1. Note base premium. 2. Add a rider. 3. Read itemized lines and total. | J69: ADB rider | K69: Rider line item displayed; total = base + rider premium. | L69: High | M69: P1 | N69: 2 | O69: @regression rider | P69: Screenshot of itemization | Q69: Automated | R69: tests/riders/riders.spec.ts | S69: Not run | U69: N | V69: Positive | W69: - | X69: Creates its own application via fixture (independent; unique generated data).
A70: TC-RID-08 | B70: Rider dependency rules are enforced | C70: Riders | D70: UI | E70: Spec: rider dependency rules | F70: QR-06 | G70: Dependency rule bypass | H70: Rider with a dependency (e.g. requires another rider or minimum face value) exists (CONFIRM). | I70: 1. Select the dependent rider without its prerequisite. 2. Add the prerequisite and select again. | J70: Dependent rider pair | K70: Blocked or flagged without prerequisite; allowed with it. Also verify: the rejected value is not saved (reload or GET shows the previous/empty value). | L70: High | M70: P2 | N70: 3 | O70: @regression rider | P70: Screenshots | Q70: Automated | R70: tests/riders/riders.spec.ts | S70: Not run | T70: Exact value/rule to be confirmed from app (see Open Items). | U70: N | V70: Negative | W70: - | X70: Creates its own application via fixture (independent; unique generated data).
A71: TC-RID-09 | B71: Removing a rider updates premium itemization and total | C71: Riders | D71: UI | E71: Spec: premium itemization | F71: QR-06, QR-05 | G71: Premium not updated after rider removal | H71: Application with one rider added. | I71: 1. Note total premium with rider. 2. Remove the rider. 3. Read itemization and total. 4. Open review page. | J71: ADB rider | K71: Rider line removed; total returns to base premium; review page matches. | L71: High | M71: P2 | N71: 3 | O71: @regression rider | P71: Screenshots | Q71: Automated | R71: tests/riders/riders.spec.ts | S71: Not run | U71: N | V71: Positive | W71: - | X71: Creates its own application via fixture (independent; unique generated data).
A72: TC-BEN-01 | B72: Add a valid primary beneficiary | C72: Beneficiaries | D72: UI | E72: BEN-V01 | F72: QR-07 | G72: Beneficiary cannot be added | H72: Application at Beneficiaries step. | I72: 1. Fill valid individual beneficiary details with 100%. 2. Save. | J72: Generated adult beneficiary | K72: Beneficiary card/row appears; running total 100%. | L72: High | M72: P1 | N72: 1 | O72: @smoke @regression beneficiary | P72: Screenshot | Q72: Automated | R72: tests/beneficiaries/beneficiaries.spec.ts | S72: Not run | U72: Y | V72: Positive | W72: - | X72: Creates its own application via fixture (independent; unique generated data).
A73: TC-BEN-02 | B73: Primary allocation below 100% blocks progression | C73: Beneficiaries | D73: UI | E73: BEN-V02 | F73: QR-07 | G73: Allocation not 100% accepted | H73: One primary beneficiary. | I73: 1. Set primary total to 99%. 2. Proceed. | J73: 99% | K73: Error shown; progression blocked. Also verify: the rejected value is not saved (reload or GET shows the previous/empty value). | L73: Critical | M73: P1 | N73: 2 | O73: @regression beneficiary | P73: Screenshot | Q73: Automated | R73: tests/beneficiaries/allocation.spec.ts | S73: Not run | U73: Y | V73: Boundary | W73: API: POST /validate returns allocation error | X73: Creates its own application via fixture (independent; unique generated data).
A74: TC-BEN-03 | B74: Primary allocation above 100% blocks progression | C74: Beneficiaries | D74: UI | E74: BEN-V03 | F74: QR-07 | G74: Allocation not 100% accepted | H74: Primary beneficiaries present. | I74: 1. Set primary total to 101%. 2. Proceed. | J74: 101% | K74: Error shown; progression blocked. Also verify: the rejected value is not saved (reload or GET shows the previous/empty value). | L74: Critical | M74: P1 | N74: 2 | O74: @regression beneficiary | P74: Screenshot | Q74: Automated | R74: tests/beneficiaries/allocation.spec.ts | S74: Not run | U74: Y | V74: Boundary | W74: - | X74: Creates its own application via fixture (independent; unique generated data).
A75: TC-BEN-04 | B75: Secondary allocation is validated separately | C75: Beneficiaries | D75: UI | E75: BEN-V04 | F75: QR-07 | G75: Secondary total not validated | H75: Primary at 100%. | I75: 1. Add secondary beneficiaries totalling 90%. 2. Proceed. 3. Correct to 100%. | J75: Secondary 90% then 100% | K75: 90% blocks with separate secondary-total error; 100% accepted; primary total unaffected. Also verify: the rejected value is not saved (reload or GET shows the previous/empty value). | L75: High | M75: P2 | N75: 2 | O75: @regression beneficiary | P75: Screenshots | Q75: Automated | R75: tests/beneficiaries/allocation.spec.ts | S75: Not run | U75: N | V75: Boundary | W75: - | X75: Creates its own application via fixture (independent; unique generated data).
A76: TC-BEN-05 | B76: Minor beneficiary requires guardian details | C76: Beneficiaries | D76: UI | E76: BEN-V05 | F76: QR-07 | G76: Minor without guardian accepted | H76: At Beneficiaries step. | I76: 1. Add beneficiary with DOB 17y364d. 2. Leave guardian blank and save. 3. Fill guardian. | J76: Minor DOB | K76: Guardian fields appear and are mandatory; blank blocked; filled accepted. Also verify: the rejected value is not saved (reload or GET shows the previous/empty value). | L76: Critical | M76: P1 | N76: 2 | O76: @regression beneficiary | P76: Screenshots | Q76: Automated | R76: tests/beneficiaries/minor.spec.ts | S76: Not run | U76: Y | V76: Negative | W76: - | X76: Creates its own application via fixture (independent; unique generated data).
A77: TC-BEN-06 | B77: Trust beneficiary shows trust-specific fields | C77: Beneficiaries | D77: UI | E77: BEN-V06 | F77: QR-07 | G77: Type-specific fields missing | H77: Add beneficiary form open. | I77: 1. Select type Trust. | J77: Trust type | K77: Trust Name, Trustee Name and Trust Date fields shown and mandatory. | L77: Medium | M77: P2 | N77: 3 | O77: @regression beneficiary | P77: Screenshot | Q77: Automated | R77: tests/beneficiaries/types.spec.ts | S77: Not run | U77: N | V77: Positive | W77: - | X77: Creates its own application via fixture (independent; unique generated data).
A78: TC-BEN-07 | B78: Organization beneficiary shows organization fields | C78: Beneficiaries | D78: UI | E78: BEN-V07 | F78: QR-07 | G78: Type-specific fields missing | H78: Add beneficiary form open. | I78: 1. Select type Organization. | J78: Organization type | K78: Registration and contact fields shown and mandatory. | L78: Medium | M78: P2 | N78: 3 | O78: @regression beneficiary | P78: Screenshot | Q78: Automated | R78: tests/beneficiaries/types.spec.ts | S78: Not run | U78: N | V78: Positive | W78: - | X78: Creates its own application via fixture (independent; unique generated data).
A79: TC-BEN-08 | B79: Duplicate beneficiary (Name + DOB + Relationship) is blocked | C79: Beneficiaries | D79: UI | E79: BEN-V08 | F79: QR-07 | G79: Duplicates allowed | H79: One beneficiary already added. | I79: 1. Add second beneficiary with same name, DOB and relationship. | J79: Duplicate record | K79: Duplicate error displayed; second record not added. Also verify: the rejected value is not saved (reload or GET shows the previous/empty value). | L79: High | M79: P1 | N79: 2 | O79: @regression beneficiary | P79: Screenshot | Q79: Automated | R79: tests/beneficiaries/duplicates.spec.ts | S79: Not run | U79: N | V79: Negative | W79: - | X79: Creates its own application via fixture (independent; unique generated data).
A80: TC-BEN-09 | B80: Removing a beneficiary updates the allocation total | C80: Beneficiaries | D80: UI | E80: BEN-V09 | F80: QR-07 | G80: Removal leaves wrong total | H80: Two primary beneficiaries 60% / 40%. | I80: 1. Remove the 40% beneficiary. 2. Read running total. | J80: 60/40 split | K80: Running total updates to 60% and the 100% error appears. | L80: High | M80: P2 | N80: 2 | O80: @regression beneficiary | P80: Screenshot | Q80: Automated | R80: tests/beneficiaries/allocation.spec.ts | S80: Not run | U80: N | V80: Positive | W80: - | X80: Creates its own application via fixture (independent; unique generated data).
A81: TC-BEN-10 | B81: Irrevocable designation requires legal confirmation modal | C81: Beneficiaries | D81: UI | E81: Spec: special designation | F81: QR-07 | G81: Irrevocable confirmation skipped | H81: Add beneficiary form open. | I81: 1. Mark beneficiary as irrevocable. 2. Save. 3. Cancel the modal, then retry and confirm. | J81: Irrevocable flag | K81: Confirmation modal appears; cancel keeps it unsaved as irrevocable; confirm saves. | L81: Medium | M81: P2 | N81: 3 | O81: @regression beneficiary | P81: Screenshot of modal | Q81: Automated | R81: tests/beneficiaries/special.spec.ts | S81: Not run | U81: N | V81: Positive | W81: - | X81: Creates its own application via fixture (independent; unique generated data).
A82: TC-BEN-11 | B82: At least one primary beneficiary is mandatory | C82: Beneficiaries | D82: UI | E82: Spec: primary beneficiary | F82: QR-07, QR-09 | G82: Missing primary beneficiary accepted | H82: Application with no beneficiaries. | I82: 1. Proceed from Beneficiaries step with none added. 2. Check review summary. | J82: No beneficiaries | K82: Progression/submission blocked and summary lists missing primary beneficiary. Also verify: the rejected value is not saved (reload or GET shows the previous/empty value). | L82: High | M82: P2 | N82: 3 | O82: @regression beneficiary | P82: Screenshot | Q82: Automated | R82: tests/beneficiaries/allocation.spec.ts | S82: Not run | U82: N | V82: Negative | W82: - | X82: Creates its own application via fixture (independent; unique generated data).
... A87: TC-DOC-02 | B87: Unsupported file type is rejected on Documents step | C87: Documents & Validation | D87: UI | E87: DOC-V02 | F87: QR-08 | G87: Bad file types accepted | H87: On Documents step. | I87: 1. Upload .exe and .txt files. | J87: invalid files | K87: Error message; no uploaded status. Also verify: the rejected value is not saved (reload or GET shows the previous/empty value). | L87: High | M87: P1 | N87: 2 | O87: @regression documents | P87: Screenshot | Q87: Automated | R87: tests/documents/upload.spec.ts | S87: Not run | U87: N | V87: Negative | W87: - | X87: Creates its own application via fixture (independent; unique generated data).
A88: TC-DOC-03 | B88: File above maximum size is rejected | C88: Documents & Validation | D88: UI | E88: DOC-V03 | F88: QR-08 | G88: Oversize files accepted | H88: Max size known (CONFIRM). | I88: 1. Upload file just above max size. 2. Upload file just below max. | J88: Generated files max+1 byte / max-1 byte | K88: Oversize rejected with size message; under-limit accepted. Also verify: the rejected value is not saved (reload or GET shows the previous/empty value). | L88: High | M88: P1 | N88: 2 | O88: @regression documents | P88: Screenshots | Q88: Automated | R88: tests/documents/upload.spec.ts | S88: Not run | T88: Exact value/rule to be confirmed from app (see Open Items). | U88: N | V88: Boundary | W88: API: POST documents rejects oversize | X88: Creates its own application via fixture (independent; unique generated data).
A89: TC-DOC-04 | B89: Missing mandatory document blocks submission | C89: Documents & Validation | D89: UI | E89: DOC-V04 | F89: QR-08, QR-09 | G89: Mandatory document not enforced | H89: Otherwise complete application with no KYC document. | I89: 1. Go to review. 2. Attempt to submit. | J89: No documents | K89: Summary lists missing document; submit blocked. Also verify: the rejected value is not saved (reload or GET shows the previous/empty value). | L89: Critical | M89: P1 | N89: 2 | O89: @regression documents | P89: Screenshot of summary | Q89: Automated | R89: tests/documents/upload.spec.ts | S89: Not run | U89: Y | V89: Negative | W89: - | X89: Creates its own application via fixture (independent; unique generated data).
A90: TC-DOC-05 | B90: Uploaded document status persists after reload and resume | C90: Documents & Validation | D90: UI | E90: Spec: upload confirmation/status | F90: QR-08, QR-10 | G90: Upload status not stored | H90: Valid document uploaded. | I90: 1. Upload valid PDF. 2. Reload page. 3. Resume from dashboard. | J90: valid.pdf | K90: Document still listed as uploaded with correct name/status. | L90: Medium | M90: P2 | N90: 3 | O90: @regression documents | P90: Screenshots | Q90: Automated | R90: tests/documents/upload.spec.ts | S90: Not run | U90: N | V90: Positive | W90: - | X90: Creates its own application via fixture (independent; unique generated data).
A91: TC-VAL-01 | B91: Validation summary lists all unresolved errors grouped | C91: Documents & Validation | D91: UI | E91: VAL-V01 | F91: QR-08 | G91: Summary stale or incomplete | H91: Incomplete application with several known gaps. | I91: 1. Open /review for incomplete application. 2. Read summary. | J91: Application missing client, doc, beneficiary data | K91: Each known gap is listed, grouped by section; no phantom errors. | L91: High | M91: P1 | N91: 2 | O91: @regression documents | P91: Screenshot of summary | Q91: Automated | R91: tests/documents/validation-summary.spec.ts | S91: Not run | U91: N | V91: Positive | W91: - | X91: Creates its own application via fixture (independent; unique generated data).
A92: TC-VAL-02 | B92: Clicking a validation error navigates to the field | C92: Documents & Validation | D92: UI | E92: VAL-V02 | F92: QR-08 | G92: Error link does not focus field | H92: Summary showing at least one error. | I92: 1. Click an item in the summary. | J92: Any error item | K92: App navigates to the related section and focuses the field. | L92: Medium | M92: P2 | N92: 3 | O92: @regression documents | P92: Screenshot / focus assertion | Q92: Automated | R92: tests/documents/validation-summary.spec.ts | S92: Not run | U92: N | V92: Positive | W92: - | X92: Creates its own application via fixture (independent; unique generated data).
A93: TC-VAL-03 | B93: Submit stays disabled until critical errors are resolved | C93: Documents & Validation | D93: UI | E93: VAL-V03 | F93: QR-08, QR-09 | G93: Submit enabled with errors | H93: Application with critical errors. | I93: 1. Open /review for an application with critical errors; check Submit state. 2. Fix every error. 3. Re-check Submit state. | J93: Application from TC-VAL-01 | K93: Disabled while errors exist; enabled when clean; summary refreshes after upstream change (not stale). Also verify: the rejected value is not saved (reload or GET shows the previous/empty value). | L93: Critical | M93: P1 | N93: 1 | O93: @smoke @regression documents | P93: Screenshots at each state | Q93: Automated | R93: tests/documents/validation-summary.spec.ts | S93: Not run | U93: Y | V93: Negative | W93: - | X93: Creates its own application via fixture (independent; unique generated data).
A94: TC-VAL-04 | B94: Validation summary refreshes after upstream data changes (not stale) | C94: Documents & Validation | D94: UI | E94: Risk QR-08: summary stale | F94: QR-08 | G94: Validation summary stale | H94: Application previously clean at review (submit enabled). | I94: 1. Open /review: summary clean. 2. Go back and invalidate data (e.g. delete a beneficiary so total < 100%). 3. Return to /review. | J94: Clean application | K94: Summary now shows the new error and Submit is disabled; no stale 'clean' state. | L94: High | M94: P1 | N94: 2 | O94: @regression documents | P94: Screenshots before and after | Q94: Automated | R94: tests/documents/validation-summary.spec.ts | S94: Not run | U94: N | V94: Positive | W94: - | X94: Creates its own application via fixture (independent; unique generated data).
A95: TC-VAL-05 | B95: Review page shows data consistent with what was entered | C95: Documents & Validation | D95: UI | E95: Guideline: review consistency | F95: QR-08, QR-10 | G95: Review data differs from entered data | H95: Fully completed application. | I95: 1. Record values entered per step (client, address, product, riders, beneficiaries). 2. Open /review. 3. Compare each section. | J95: Generated application | K95: Every section on review equals entered values (names, DOB/age, product, face value, premium, riders, beneficiaries, documents). | L95: High | M95: P1 | N95: 2 | O95: @regression documents | P95: Screenshot of review + comparison log | Q95: Automated | R95: tests/documents/review.spec.ts | S95: Not run | U95: N | V95: Positive | W95: - | X95: Creates its own application via fixture (independent; unique generated data).
A96: TC-WF-01 | B96: Incomplete application can be saved as draft | C96: Submission & Status | D96: UI | E96: WF-V01 | F96: QR-10 | G96: Draft not persisted | H96: Logged in; new application started. | I96: 1. Enter partial client data. 2. Click Save draft. 3. Go to dashboard. | J96: Partial client data | K96: Dashboard shows a Draft row for the application. | L96: High | M96: P1 | N96: 2 | O96: @regression workflow | P96: Screenshot of dashboard row | Q96: Automated | R96: tests/workflow/draft.spec.ts | S96: Not run | U96: N | V96: Positive | W96: DB (if approved): status = Draft | X96: Creates its own application via fixture (independent; unique generated data).
A97: TC-WF-02 | B97: Draft resumes with saved data at correct step | C97: Submission & Status | D97: UI | E97: WF-V02 | F97: QR-10 | G97: Draft data lost | H97: Draft from TC-WF-01. | I97: 1. Open draft from dashboard. 2. Inspect values. | J97: Draft created in setup | K97: Saved values and step restored. | L97: High | M97: P1 | N97: 2 | O97: @regression workflow | P97: Screenshot | Q97: Automated | R97: tests/workflow/draft.spec.ts | S97: Not run | U97: N | V97: Positive | W97: - | X97: Creates its own application via fixture (independent; unique generated data).
A98: TC-WF-03 | B98: Valid application is submitted end to end and gets a reference number | C98: Submission & Status | D98: E2E | E98: WF-V03 | F98: QR-09 | G98: Incomplete/no reference on submit | H98: Valid agent; all test files and data available. | I98: 1. Login. 2. Start new application. 3. Complete Client, Address, KYC, Product, Riders, Beneficiaries, Documents. 4. Review summary clean. 5. Submit. 6. Read confirmation. | J98: Generated valid application | K98: Confirmation shows non-empty reference number; no validation errors. | L98: Critical | M98: P1 | N98: 1 | O98: @smoke @e2e workflow | P98: Trace of full flow; confirmation screenshot | Q98: Automated | R98: tests/workflow/e2e-submission.spec.ts | S98: Not run | U98: Y | V98: Positive | W98: API: status = Submitted; DB: reference unique | X98: Creates its own application; submission cannot be undone - unique generated data.
A99: TC-WF-04 | B99: Submitted application is read-only | C99: Submission & Status | D99: UI | E99: WF-V04 | F99: QR-09 | G99: Submitted app editable | H99: Submitted application exists. | I99: 1. Open submitted application. 2. Try editing fields and saving. | J99: Submitted application id | K99: Fields disabled/read-only; edit controls absent. | L99: High | M99: P1 | N99: 2 | O99: @regression workflow | P99: Screenshot | Q99: Automated | R99: tests/workflow/submission.spec.ts | S99: Not run | U99: N | V99: Positive | W99: API: POST update rejected for submitted application | X99: Read-only seeded submitted application.
A100: TC-WF-05 | B100: Confirmation/status message shown after submission | C100: Submission & Status | D100: UI | E100: WF-V05 | F100: QR-09 | G100: Missing confirmation | H100: Run in E2E flow. | I100: 1. Submit valid application. 2. Read confirmation page. | J100: - | K100: Confirmation message (email simulation/status) displayed. | L100: Medium | M100: P2 | N100: 2 | O100: @regression workflow | P100: Screenshot | Q100: Automated | R100: tests/workflow/submission.spec.ts | S100: Not run | U100: N | V100: Positive | W100: - | X100: Creates its own application via fixture (independent; unique generated data).
... A124: TC-XC-01 | B124: Smoke login and dashboard on Firefox and WebKit | C124: Cross-Cutting | D124: UI | E124: Risk QR-13 cross-browser | F124: QR-13 | G124: Critical flow differs on another browser | H124: Playwright projects for firefox and webkit configured. | I124: 1. Run @smoke auth and dashboard tests with --project=firefox and --project=webkit. | J124: VALID_AGENT | K124: Login and dashboard smoke pass on both browsers or differences are logged as browser defects. | L124: Medium | M124: P3 | N124: 3 | O124: @smoke cross-browser | P124: HTML report per project | Q124: Automated | R124: tests/auth/login.spec.ts (projects) | S124: Not run | U124: N | V124: Positive | W124: - | X124: Read-only (login only).

Sheet Coverage Summary
A1: Coverage by Module vs Minimum Automation Coverage
A2: Minimums are from 'Submissions and Evaluations' section 5.5 (blue = hard-coded input from the source document). Counts are live formulas on the Test Cases sheet.
A4: Module | B4: Minimum Required (60-test target) | C4: Planned Test Cases | D4: Wave 1 (Smoke) | E4: P1 Cases | F4: Critical Severity | G4: Surplus / (Gap) vs Minimum | H4: Status
A5: Authentication | B5: 6 | C5: =COUNTIF('Test Cases'!$C$2:$C$174,A5) | D5: =COUNTIFS('Test Cases'!$C$2:$C$174,A5,'Test Cases'!$N$2:$N$174,1) | E5: =COUNTIFS('Test Cases'!$C$2:$C$174,A5,'Test Cases'!$M$2:$M$174,"P1") | F5: =COUNTIFS('Test Cases'!$C$2:$C$174,A5,'Test Cases'!$L$2:$L$174,"Critical") | G5: =C5-B5 | H5: =IF(C5>=B5,"Meets minimum","GAP")
A6: Dashboard | B6: 4 | C6: =COUNTIF('Test Cases'!$C$2:$C$174,A6) | D6: =COUNTIFS('Test Cases'!$C$2:$C$174,A6,'Test Cases'!$N$2:$N$174,1) | E6: =COUNTIFS('Test Cases'!$C$2:$C$174,A6,'Test Cases'!$M$2:$M$174,"P1") | F6: =COUNTIFS('Test Cases'!$C$2:$C$174,A6,'Test Cases'!$L$2:$L$174,"Critical") | G6: =C6-B6 | H6: =IF(C6>=B6,"Meets minimum","GAP")
A7: Client Information | B7: 8 | C7: =COUNTIF('Test Cases'!$C$2:$C$174,A7) | D7: =COUNTIFS('Test Cases'!$C$2:$C$174,A7,'Test Cases'!$N$2:$N$174,1) | E7: =COUNTIFS('Test Cases'!$C$2:$C$174,A7,'Test Cases'!$M$2:$M$174,"P1") | F7: =COUNTIFS('Test Cases'!$C$2:$C$174,A7,'Test Cases'!$L$2:$L$174,"Critical") | G7: =C7-B7 | H7: =IF(C7>=B7,"Meets minimum","GAP")
A8: Address & Contact | B8: 5 | C8: =COUNTIF('Test Cases'!$C$2:$C$174,A8) | D8: =COUNTIFS('Test Cases'!$C$2:$C$174,A8,'Test Cases'!$N$2:$N$174,1) | E8: =COUNTIFS('Test Cases'!$C$2:$C$174,A8,'Test Cases'!$M$2:$M$174,"P1") | F8: =COUNTIFS('Test Cases'!$C$2:$C$174,A8,'Test Cases'!$L$2:$L$174,"Critical") | G8: =C8-B8 | H8: =IF(C8>=B8,"Meets minimum","GAP")
A9: KYC & Financial | B9: 6 | C9: =COUNTIF('Test Cases'!$C$2:$C$174,A9) | D9: =COUNTIFS('Test Cases'!$C$2:$C$174,A9,'Test Cases'!$N$2:$N$174,1) | E9: =COUNTIFS('Test Cases'!$C$2:$C$174,A9,'Test Cases'!$M$2:$M$174,"P1") | F9: =COUNTIFS('Test Cases'!$C$2:$C$174,A9,'Test Cases'!$L$2:$L$174,"Critical") | G9: =C9-B9 | H9: =IF(C9>=B9,"Meets minimum","GAP")
A10: Product & Policy | B10: 6 | C10: =COUNTIF('Test Cases'!$C$2:$C$174,A10) | D10: =COUNTIFS('Test Cases'!$C$2:$C$174,A10,'Test Cases'!$N$2:$N$174,1) | E10: =COUNTIFS('Test Cases'!$C$2:$C$174,A10,'Test Cases'!$M$2:$M$174,"P1") | F10: =COUNTIFS('Test Cases'!$C$2:$C$174,A10,'Test Cases'!$L$2:$L$174,"Critical") | G10: =C10-B10 | H10: =IF(C10>=B10,"Meets minimum","GAP")
A11: Riders | B11: 5 | C11: =COUNTIF('Test Cases'!$C$2:$C$174,A11) | D11: =COUNTIFS('Test Cases'!$C$2:$C$174,A11,'Test Cases'!$N$2:$N$174,1) | E11: =COUNTIFS('Test Cases'!$C$2:$C$174,A11,'Test Cases'!$M$2:$M$174,"P1") | F11: =COUNTIFS('Test Cases'!$C$2:$C$174,A11,'Test Cases'!$L$2:$L$174,"Critical") | G11: =C11-B11 | H11: =IF(C11>=B11,"Meets minimum","GAP")
A12: Beneficiaries | B12: 7 | C12: =COUNTIF('Test Cases'!$C$2:$C$174,A12) | D12: =COUNTIFS('Test Cases'!$C$2:$C$174,A12,'Test Cases'!$N$2:$N$174,1) | E12: =COUNTIFS('Test Cases'!$C$2:$C$174,A12,'Test Cases'!$M$2:$M$174,"P1") | F12: =COUNTIFS('Test Cases'!$C$2:$C$174,A12,'Test Cases'!$L$2:$L$174,"Critical") | G12: =C12-B12 | H12: =IF(C12>=B12,"Meets minimum","GAP")
A13: Documents & Validation | B13: 4 | C13: =COUNTIF('Test Cases'!$C$2:$C$174,A13) | D13: =COUNTIFS('Test Cases'!$C$2:$C$174,A13,'Test Cases'!$N$2:$N$174,1) | E13: =COUNTIFS('Test Cases'!$C$2:$C$174,A13,'Test Cases'!$M$2:$M$174,"P1") | F13: =COUNTIFS('Test Cases'!$C$2:$C$174,A13,'Test Cases'!$L$2:$L$174,"Critical") | G13: =C13-B13 | H13: =IF(C13>=B13,"Meets minimum","GAP")
A14: Submission & Status | B14: 5 | C14: =COUNTIF('Test Cases'!$C$2:$C$174,A14) | D14: =COUNTIFS('Test Cases'!$C$2:$C$174,A14,'Test Cases'!$N$2:$N$174,1) | E14: =COUNTIFS('Test Cases'!$C$2:$C$174,A14,'Test Cases'!$M$2:$M$174,"P1") | F14: =COUNTIFS('Test Cases'!$C$2:$C$174,A14,'Test Cases'!$L$2:$L$174,"Critical") | G14: =C14-B14 | H14: =IF(C14>=B14,"Meets minimum","GAP")
A15: API | B15: 8 | C15: =COUNTIF('Test Cases'!$C$2:$C$174,A15) | D15: =COUNTIFS('Test Cases'!$C$2:$C$174,A15,'Test Cases'!$N$2:$N$174,1) | E15: =COUNTIFS('Test Cases'!$C$2:$C$174,A15,'Test Cases'!$M$2:$M$174,"P1") | F15: =COUNTIFS('Test Cases'!$C$2:$C$174,A15,'Test Cases'!$L$2:$L$174,"Critical") | G15: =C15-B15 | H15: =IF(C15>=B15,"Meets minimum","GAP")
A16: Cross-Cutting | B16: 0 | C16: =COUNTIF('Test Cases'!$C$2:$C$174,A16) | D16: =COUNTIFS('Test Cases'!$C$2:$C$174,A16,'Test Cases'!$N$2:$N$174,1) | E16: =COUNTIFS('Test Cases'!$C$2:$C$174,A16,'Test Cases'!$M$2:$M$174,"P1") | F16: =COUNTIFS('Test Cases'!$C$2:$C$174,A16,'Test Cases'!$L$2:$L$174,"Critical") | G16: =C16-B16 | H16: =IF(C16>=B16,"Meets minimum","GAP")
A17: TOTAL | B17: =SUM(B5:B16) | C17: =SUM(C5:C16) | D17: =SUM(D5:D16) | E17: =SUM(E5:E16) | F17: =SUM(F5:F16) | G17: =SUM(G5:G16) | H17: =IF(C17>=B17,"Meets 60","Below 60")
A19: Reduced-scope option
A20: Short-cohort set (30-35 tests): Wave 1 + all Critical cases + 5 extras (lockout, rider rules, premium) so auth, one E2E, allocation, rider rules, API and reporting stay covered. Count flagged 'Y': | D20: =COUNTIF('Test Cases'!$U$2:$U$174,"Y")
A21: Wave 1 (smoke) cases: | D21: =COUNTIF('Test Cases'!$N$2:$N$174,1)
A23: Automation progress
A24: Not started | D24: =COUNTIF('Test Cases'!$Q$2:$Q$174,A24)
A25: In progress | D25: =COUNTIF('Test Cases'!$Q$2:$Q$174,A25)
A26: Automated | D26: =COUNTIF('Test Cases'!$Q$2:$Q$174,A26)
A27: Manual only | D27: =COUNTIF('Test Cases'!$Q$2:$Q$174,A27)
A28: Blocked | D28: =COUNTIF('Test Cases'!$Q$2:$Q$174,A28)
A29: Not applicable | D29: =COUNTIF('Test Cases'!$Q$2:$Q$174,A29)
A31: Test type split
A32: UI | D32: =COUNTIF('Test Cases'!$D$2:$D$174,A32)
A33: API | D33: =COUNTIF('Test Cases'!$D$2:$D$174,A33)
A34: E2E | D34: =COUNTIF('Test Cases'!$D$2:$D$174,A34)
A36: Scenario mix (guards against happy-path-only suites)
A37: Positive | D37: =COUNTIF('Test Cases'!$V$2:$V$174,A37) | E37: =D37/SUM($D$37:$D$39)
A38: Negative | D38: =COUNTIF('Test Cases'!$V$2:$V$174,A38) | E38: =D38/SUM($D$37:$D$39)
A39: Boundary | D39: =COUNTIF('Test Cases'!$V$2:$V$174,A39) | E39: =D39/SUM($D$37:$D$39)
A40: Negative + Boundary share (target: at least 50%) | D40: =(D38+D39)/SUM(D37:D39)

Sheet Risk Traceability
A1: Traceability: Submission 1 Risk Register (QR-01..QR-14) to Test Cases
A3: Risk ID | B3: Area | C3: Risk (from Submission 1) | D3: Priority | E3: # Test Cases | F3: Coverage
A4: QR-01 | B4: Authentication | C4: Unauthorized protected-route or API access | D4: Critical | E4: =COUNTIF('Test Cases'!$F$2:$F$174,"*"&A4&"*") | F4: =IF(E4>0,"Covered by test cases",IF(OR(A4="QR-11",A4="QR-12",A4="QR-13",A4="QR-14"),"Covered by framework/config","GAP"))
A5: QR-02 | B5: Dashboard | C5: Cross-agent data exposure or incorrect status | D5: Critical | E5: =COUNTIF('Test Cases'!$F$2:$F$174,"*"&A5&"*") | F5: =IF(E5>0,"Covered by test cases",IF(OR(A5="QR-11",A5="QR-12",A5="QR-13",A5="QR-14"),"Covered by framework/config","GAP"))
A6: QR-03 | B6: Client | C6: DOB boundary or age calculation failure | D6: Critical | E6: =COUNTIF('Test Cases'!$F$2:$F$174,"*"&A6&"*") | F6: =IF(E6>0,"Covered by test cases",IF(OR(A6="QR-11",A6="QR-12",A6="QR-13",A6="QR-14"),"Covered by framework/config","GAP"))
A7: QR-04 | B7: KYC/Compliance | C7: Sensitive ID exposure or mandatory evidence bypass | D7: Critical | E7: =COUNTIF('Test Cases'!$F$2:$F$174,"*"&A7&"*") | F7: =IF(E7>0,"Covered by test cases",IF(OR(A7="QR-11",A7="QR-12",A7="QR-13",A7="QR-14"),"Covered by framework/config","GAP"))
A8: QR-05 | B8: Product/Premium | C8: Invalid configuration or inconsistent premium | D8: Critical | E8: =COUNTIF('Test Cases'!$F$2:$F$174,"*"&A8&"*") | F8: =IF(E8>0,"Covered by test cases",IF(OR(A8="QR-11",A8="QR-12",A8="QR-13",A8="QR-14"),"Covered by framework/config","GAP"))
A9: QR-06 | B9: Riders | C9: Eligibility, coverage, count or exclusion rule bypass | D9: Critical | E9: =COUNTIF('Test Cases'!$F$2:$F$174,"*"&A9&"*") | F9: =IF(E9>0,"Covered by test cases",IF(OR(A9="QR-11",A9="QR-12",A9="QR-13",A9="QR-14"),"Covered by framework/config","GAP"))
A10: QR-07 | B10: Beneficiaries | C10: Invalid allocation, duplicate or missing guardian accepted | D10: Critical | E10: =COUNTIF('Test Cases'!$F$2:$F$174,"*"&A10&"*") | F10: =IF(E10>0,"Covered by test cases",IF(OR(A10="QR-11",A10="QR-12",A10="QR-13",A10="QR-14"),"Covered by framework/config","GAP"))
A11: QR-08 | B11: Documents/Review | C11: Invalid upload or stale validation summary | D11: High | E11: =COUNTIF('Test Cases'!$F$2:$F$174,"*"&A11&"*") | F11: =IF(E11>0,"Covered by test cases",IF(OR(A11="QR-11",A11="QR-12",A11="QR-13",A11="QR-14"),"Covered by framework/config","GAP"))
A12: QR-09 | B12: Submission | C12: Incomplete case submits or reference/state is wrong | D12: Critical | E12: =COUNTIF('Test Cases'!$F$2:$F$174,"*"&A12&"*") | F12: =IF(E12>0,"Covered by test cases",IF(OR(A12="QR-11",A12="QR-12",A12="QR-13",A12="QR-14"),"Covered by framework/config","GAP"))
A13: QR-10 | B13: Persistence | C13: Draft or submitted values not saved accurately | D13: High | E13: =COUNTIF('Test Cases'!$F$2:$F$174,"*"&A13&"*") | F13: =IF(E13>0,"Covered by test cases",IF(OR(A13="QR-11",A13="QR-12",A13="QR-13",A13="QR-14"),"Covered by framework/config","GAP"))
A14: QR-11 | B14: Automation | C14: Flaky checks or weak evidence hides true result | D14: Medium | E14: =COUNTIF('Test Cases'!$F$2:$F$174,"*"&A14&"*") | F14: =IF(E14>0,"Covered by test cases",IF(OR(A14="QR-11",A14="QR-12",A14="QR-13",A14="QR-14"),"Covered by framework/config","GAP"))
A15: QR-12 | B15: Test Data | C15: Seed collision or reset changes expected state | D15: High | E15: =COUNTIF('Test Cases'!$F$2:$F$174,"*"&A15&"*") | F15: =IF(E15>0,"Covered by test cases",IF(OR(A15="QR-11",A15="QR-12",A15="QR-13",A15="QR-14"),"Covered by framework/config","GAP"))
... A17: QR-14 | B17: Environment | C17: Shared service or dependency prevents valid testing | D17: High | E17: =COUNTIF('Test Cases'!$F$2:$F$174,"*"&A17&"*") | F17: =IF(E17>0,"Covered by test cases",IF(OR(A17="QR-11",A17="QR-12",A17="QR-13",A17="QR-14"),"Covered by framework/config","GAP"))
A19: QR-11 to QR-14 are addressed by framework design, not individual test cases: stable locators and trace/screenshot config (QR-11), unique generated data per run plus reserved seed users (QR-12), the Chromium/Firefox/WebKit projects in playwright.config.ts (QR-13), and a health-check / global-setup step (QR-14). They are documented in the README.

Sheet Validation ID Matrix
A1: Every Validation ID in the problem statement mapped to a test case
A3: Validation ID | B3: Scenario (from Functional Module Descriptions) | C3: Mapped Test Case(s) | D3: # Mapped | E3: Status
A4: AUTH-V01 | B4: Valid agent can log in successfully | C4: TC-AUTH-01 | D4: =COUNTIF('Test Cases'!$E$2:$E$174,"*"&A4&"*") | E4: =IF(D4>0,"Covered","GAP")
A5: AUTH-V02 | B5: Invalid password displays correct error message | C5: TC-AUTH-02 | D5: =COUNTIF('Test Cases'!$E$2:$E$174,"*"&A5&"*") | E5: =IF(D5>0,"Covered","GAP")
A6: AUTH-V03 | B6: Blank username and password show mandatory validation | C6: TC-AUTH-03 | D6: =COUNTIF('Test Cases'!$E$2:$E$174,"*"&A6&"*") | E6: =IF(D6>0,"Covered","GAP")
A7: AUTH-V04 | B7: Logout clears session and redirects to login page | C7: TC-AUTH-04 | D7: =COUNTIF('Test Cases'!$E$2:$E$174,"*"&A7&"*") | E7: =IF(D7>0,"Covered","GAP")
A8: AUTH-V05 | B8: Direct access to dashboard without login is blocked | C8: TC-AUTH-05 | D8: =COUNTIF('Test Cases'!$E$2:$E$174,"*"&A8&"*") | E8: =IF(D8>0,"Covered","GAP")
A9: AUTH-V06 | B9: Locked user cannot access dashboard | C9: TC-AUTH-06 | D9: =COUNTIF('Test Cases'!$E$2:$E$174,"*"&A9&"*") | E9: =IF(D9>0,"Covered","GAP")
A10: AUTH-V07 | B10: Account locks after five failed login attempts | C10: TC-AUTH-07 | D10: =COUNTIF('Test Cases'!$E$2:$E$174,"*"&A10&"*") | E10: =IF(D10>0,"Covered","GAP")
A11: AUTH-V08 | B11: Password policy rejects weak password | C11: TC-AUTH-08 | D11: =COUNTIF('Test Cases'!$E$2:$E$174,"*"&A11&"*") | E11: =IF(D11>0,"Covered","GAP")
A12: DASH-V01 | B12: Dashboard loads after successful login | C12: TC-DASH-01 | D12: =COUNTIF('Test Cases'!$E$2:$E$174,"*"&A12&"*") | E12: =IF(D12>0,"Covered","GAP")
A13: DASH-V02 | B13: Agent sees only own applications | C13: TC-DASH-02 | D13: =COUNTIF('Test Cases'!$E$2:$E$174,"*"&A13&"*") | E13: =IF(D13>0,"Covered","GAP")
A14: DASH-V03 | B14: New agent sees empty application state | C14: TC-DASH-03 | D14: =COUNTIF('Test Cases'!$E$2:$E$174,"*"&A14&"*") | E14: =IF(D14>0,"Covered","GAP")
A15: DASH-V04 | B15: Draft application can be resumed | C15: TC-DASH-04 | D15: =COUNTIF('Test Cases'!$E$2:$E$174,"*"&A15&"*") | E15: =IF(D15>0,"Covered","GAP")
... A72: API-V08 | B72: Applications API returns only logged-in agent records | C72: TC-API-08 | D72: =COUNTIF('Test Cases'!$E$2:$E$174,"*"&A72&"*") | E72: =IF(D72>0,"Covered","GAP")
B74: Validation IDs without a test case: | D74: =COUNTIF(E4:E72,"GAP")

Sheet Test Data
A1: Controlled Test Data (generated per run; never hard-code in specs)
A2: Boundary DOBs are formulas relative to today so the sheet always shows the dates for the day you read it. dataGenerator.ts must compute the same values at run time.
A4: Dataset | B4: Date of Birth (calculated) | C4: Expected Outcome | D4: Used By
A5: Underage - 17 years 364 days | B5: =EDATE(TODAY(),-216)+1 | C5: Rejected (below 18) | D5: TC-CLI-03, TC-API-03, TC-BEN-05 (as minor)
A6: Exactly 18 years | B6: =EDATE(TODAY(),-216) | C6: Accepted (confirm inclusive) | D6: TC-CLI-06
A7: Typical adult - 40 years | B7: =EDATE(TODAY(),-480) | C7: Accepted | D7: TC-CLI-01, TC-WF-03
A8: Exactly 65 years | B8: =EDATE(TODAY(),-780) | C8: Accepted (confirm inclusive) | D8: TC-CLI-06
A9: Over 65 - 65 years + 1 day | B9: =EDATE(TODAY(),-780)-1 | C9: Rejected (above 65) | D9: TC-CLI-04
A10: Future date - tomorrow | B10: =TODAY()+1 | C10: Rejected | D10: TC-CLI-05, TC-API-03
A12: Allocation datasets
A13: Scenario | B13: Primary % | C13: Secondary % | D13: Expected
A14: Exact | B14: 100 | C14: 100 | D14: Accepted
A15: Under | B15: 99 | C15: - | D15: Blocked
A16: Over | B16: 101 | C16: - | D16: Blocked
A17: Split 60/40 | B17: 60 + 40 | C17: - | D17: Accepted; removing 40 leaves 60 -> error
A18: Secondary short | B18: 100 | C18: 90 | D18: Blocked (secondary total)
A21: Upload files (fixtures/files)
A22: File | B22: Type / Size | C22: Expected | D22: Used By
A23: valid.pdf | B23: PDF, ~50 KB | C23: Accepted | D23: TC-DOC-01
A24: valid.jpg | B24: JPG, ~50 KB | C24: Accepted | D24: TC-DOC-01
A25: valid.png | B25: PNG, ~50 KB | C25: Accepted | D25: TC-DOC-01
A26: invalid.exe | B26: EXE (renamed dummy) | C26: Rejected - type | D26: TC-KYC-03, TC-DOC-02
A27: invalid.txt | B27: TXT | C27: Rejected - type | D27: TC-KYC-03, TC-DOC-02
A28: under-limit.pdf | B28: max size - 1 byte (CONFIRM max) | C28: Accepted | D28: TC-DOC-03
A29: over-limit.pdf | B29: max size + 1 byte (CONFIRM max) | C29: Rejected - size | D29: TC-DOC-03
A32: Environment variables (.env.example placeholders - no real values)
A33: Variable | B33: Purpose | C33: Placeholder
A34: BASE_URL | B34: App base URL | C34: http://127.0.0.1:8081
A35: APP_NAME | B35: insurance or finserve | C35: insurance
A36: VALID_AGENT_USER / _PASS | B36: Happy path agent | C36: <from seed data doc>
A37: SECOND_AGENT_USER / _PASS | B37: Data isolation | C37: <from seed data doc>
A38: NEW_AGENT_USER / _PASS | B38: Empty dashboard | C38: <from seed data doc>
A39: LOCKED_AGENT_USER / _PASS | B39: Locked message | C39: <from seed data doc>
A40: LOCKOUT_TEST_AGENT_USER / _PASS | B40: Reserved for 5-attempt lock test | C40: <from seed data doc>
A41: MFA_AGENT_USER / _PASS / MFA_OTP | B41: OTP login | C41: <from seed data doc>
A42: API_BASE_URL | B42: API root | C42: ${BASE_URL}/api
A43: SEEDED_DRAFT_ID / SEEDED_SUBMITTED_ID | B43: Resume and read-only checks | C43: <from seed data doc>

Sheet Open Items
A1: Values to confirm from the running app / mentor before asserting exact results
A3: # | B3: Item to confirm | C3: Why it matters | D3: Affected Test Cases | E3: Resolution (fill in) | F3: Status
A4: 1 | B4: Insurance app port (8081 vs 8082) and base URL | C4: FinServe app also runs in the lab | D4: All | F4: Open
A5: 2 | B5: Seed users, passwords, MFA OTP value, lockout reset method | C5: Auth and isolation tests | D5: TC-AUTH-*, TC-DASH-02/03, TC-API-08 | F5: Open
A6: 3 | B6: Are ages 18 and 65 inclusive? Timezone for age calculation? | C6: Boundary assertions | D6: TC-CLI-03/04/06 | F6: Open
A7: 4 | B7: Password policy and failed-attempt/lock-reset rules | C7: Exact weak-password set | D7: TC-AUTH-07/08/11 | F7: Open
A8: 5 | B8: Product face value min/max, payment and policy terms, active vs inactive products | C8: Boundary values | D8: TC-PROD-* | F8: Open
A9: 6 | B9: Premium formula/rounding or API field exposing premium | C9: Recalculation assertions | D9: TC-PROD-05/06, TC-RID-07 | F9: Open
A10: 7 | B10: Rider age limits, max rider count, coverage caps, waiver pair | C10: Rider decision table | D10: TC-RID-* | F10: Open
A11: 8 | B11: ID types and number formats; SSN mask format | C11: KYC validation | D11: TC-KYC-01/02/07 | F11: Open
A12: 9 | B12: Affordability rule (income vs premium) | C12: Warning vs block | D12: TC-KYC-05 | F12: Open
A13: 10 | B13: Allowed file types, max file size, mandatory documents by scenario | C13: Upload tests | D13: TC-KYC-03, TC-DOC-* | F13: Open
A14: 11 | B14: Duplicate beneficiary exact key and irrevocable modal wording | C14: Duplicate/special tests | D14: TC-BEN-08/10 | F14: Open
A15: 12 | B15: Seeded defect catalog / defect codes | C15: Replace descriptive defect links with codes | D15: All (column G) | F15: Open
... A23: 20 | B23: Dashboard and catalog search fields (name, reference, product) | C23: Search assertions | D23: TC-DASH-07, TC-PROD-13 | F23: Open

Sheet Review Log
A1: Reviewer Findings and Changes Applied (v2 review against Submission 2 documents)
A3: # | B3: Type | C3: Finding | D3: Source requirement | E3: Action taken | F3: Test case(s)
A4: 1 | B4: Gap | C4: No test for session timeout / expiry | D4: Auth automation focus: session timeout; Sub 1 path 'Session expiration' | E4: Added session-expiry test | F4: TC-AUTH-12
A5: 2 | B5: Gap | C5: Pending (unapproved) agent role not tested | D5: Auth user types; Sub 1 roles table | E5: Added pending-agent access test | F5: TC-AUTH-13
A6: 3 | B6: Gap | C6: Dashboard search and profile/support routes not covered | D6: Dashboard: search, filters; routes /profile, /support | E6: Added search and route tests | F6: TC-DASH-07, TC-DASH-09
A7: 4 | B7: Gap | C7: Cross-agent access only tested via lists, not direct URL | D7: Risk QR-02 (Critical) | E7: Added direct-URL isolation test | F7: TC-DASH-08
A8: 5 | B8: Gap | C8: Impossible/malformed DOB values not tested | D8: Client DOB boundaries, date validation | E8: Added malformed DOB test | F8: TC-CLI-09
A9: 6 | B9: Gap | C9: Financial suitability fields (income, net worth, source of funds, risk profile) and ID expiry not validated | D9: KYC and financial spec | E9: Added two KYC tests | F9: TC-KYC-08, TC-KYC-09
A10: 7 | B10: Gap | C10: Product eligibility vs client age was missing although listed in problem statement 2.2 | D10: Problem statement 2.2 | E10: Added eligibility test (High, P1) | F10: TC-PROD-10
A11: 8 | B11: Gap | C11: Payment/policy term rules, invalid face-value inputs, catalog search and UI-vs-API premium not covered | D11: Product spec table; ProductCatalogPage; premium API reconciliation | E11: Added four product tests | F11: TC-PROD-11..14
A12: 9 | B12: Gap | C12: Rider dependency rules and rider removal not covered | D12: Rider spec: dependency rules; premium itemization | E12: Added two rider tests | F12: TC-RID-08, TC-RID-09
A13: 10 | B13: Gap | C13: Beneficiary edit, invalid allocation inputs and persistence not covered | D13: Beneficiary spec: add/edit/remove; allocation; persistence | E13: Added three beneficiary tests | F13: TC-BEN-12..14
A14: 11 | B14: Gap | C14: Validation summary staleness was bundled inside the submit-gating test; review data consistency and upload persistence missing | D14: Guideline: review consistency; Risk QR-08 | E14: Split stale-summary into its own test; added review-consistency and upload-persistence tests | F14: TC-VAL-03/04/05, TC-DOC-05
A15: 12 | B15: Gap | C15: No smoke path that stops at review (guideline build step 5); no double-submit, confirmation gating or submitted-data persistence tests | D15: Guideline 4 step 5; Risk QR-09, QR-10 | E15: Added four workflow tests | F15: TC-WF-10..13
... A28: 25 | B28: Quality | C28: Short-cohort fallback was a loose rule | D28: Min coverage 30-35 option | E28: Defined an explicit flagged set that keeps auth, E2E, allocation, rider rules, API | F28: Short-Cohort Set = Y
